Workbook

Sheet Topic_words
B1: topic | C1: topic_distribution
A2: =IF(COUNTIF(Topic_importance!$A$2:$A$21,Topic_words!B2),1,0) -> 1 | B2: 0 | C2: {'asset': np.float64(0.88078287225586), 'activity': np.float64(0.31787455908177226), 'also': np.float64(0.28855921863405226), 'account': np.float64(0.11253551474809065), 'area': np.float64(0.08390375585003117), 'action': np.float64(0.08219763156052116), 'approval': np.float64(0.06333951502962484), 'act': np.float64(0.05120364765108197), 'aim': np.float64(0.04238249047644732), 'asia': np.float64(0.029645263379161943), 'amt': np.float64(0.028859100410800472), 'remaining': np.float64(0.023847838963113193), 'agreed': np.float64(0.018012145893573736), 'even': np.float64(0.01730848535310542), 'association': np.float64(0.01653758404919214), 'icaap': np.float64(0.015168892852630757), 'bbb': np.float64(0.014443011867123727), 'usa': np.float64(0.013677688772761772), 'iaa': np.float64(0.012024625171166866), 'iaaa': np.float64(0.012024625171166866), 'ama': np.float64(0.011962837342979597), 'eve': np.float64(0.010164964392125114), 'etc': np.float64(0.008710646145723805), 'aaa': np.float64(0.007517534328866078), 'ccc': np.float64(0.00690896913571638), 'assist': np.float64(0.006616278999680272), 'acute': np.float64(0.006198593254320788), 'baa': np.float64(0.006150471970222687), 'erc': np.float64(0.006021579508125208), 'aear': np.float64(0.005975883301615032), 'approve': np.float64(0.00560721792105267), 'caa': np.float64(0.00551618057353995), 'avg': np.float64(0.005398671411700234), 'afc': np.float64(0.005143955021559263), 'abcp': np.float64(0.005080164615097583), 'bac': np.float64(0.004864829601325589), 'alm': np.float64(0.0046368838966748685), 'aware': np.float64(0.0039854047169597204), 'always': np.float64(0.003928119897855127), 'alert': np.float64(0.0039047503901806753), 'aml': np.float64(0.0031921463061460784), 'alia': np.float64(0.002672535981602553), 'agent': np.float64(0.0024893900024677996), 'assignment': np.float64(0.002435461913458983), 'alpha': np.float64(0.002404925034233373), 'attribute': np.float64(0.0021272214988738813), 'iam': np.float64(0.0019017125042198593), 'arching': np.float64(0.0017497277947295332), 'rtc': np.float64(0.0016054614320566108), 'rea': np.float64(0.0015811766969675007), 'ima': np.float64(0.001575893640901832), 'agm': np.float64(0.001457119284649872), 'automatic': np.float64(0.0013959944155440504), 'eea': np.float64(0.0013706422161678126), 'axis': np.float64(0.0012024625171166866), 'ups': np.float64(0.0010815346724446326), 'acams': np.float64(0.0010758862512242067), 'auto': np.float64(0.0010490105099695312), 'psps': np.float64(0.0010002399929142163), 'ante': np.float64(0.0009729659202651181), 'edd': np.float64(0.0008675260907957583), 'jsc': np.float64(0.0008229732309511755), 'avatar': np.float64(0.0006682099061850352), 'ooo': np.float64(0.0006682099061850352), 'app': np.float64(0.0006661257200085572), 'asf': np.float64(0.00065519723950384), 'aside': np.float64(0.00065519723950384), 'amc': np.float64(0.0006029277206367138), 'ago': np.float64(0.0005461839581781782), 'accountse': np.float64(0.0005059715590774956), 'assetsa': np.float64(0.0005059715590774956), 'administrator': np.float64(0.0005001199964571082), 'aud': np.float64(0.0004937839385707052), 'ras': np.float64(0.0004876285205428518), 'assetsb': np.float64(0.0004811248822671416), 'authentication': np.float64(0.00045749839012124274), 'era': np.float64(0.0004189518152861614), 'aug': np.float64(0.0004057409958148943), 'apr': np.float64(0.00039943494808064356), 'aid': np.float64(0.00038489044623565193), 'reas': np.float64(0.0003014638603183569), 'asking': np.float64(0.000293594416325018), 'agement': np.float64(0.00026033234920137447), 'afca': np.float64(0.0002500599982285541), 'alfa': np.float64(0.0001822107837104323), 'aum': np.float64(0.00017886577444283622), 'acc': np.float64(0.00015877982105030745), 'apps': np.float64(0.00015034979963322512), 'aiver': np.float64(0.0001444247527058504), 'asse': np.float64(0.0001444247527058504), 'rre': np.float64(0.00012534314236113098), 'ate': np.float64(9.122165946250846e-05), 'ari': np.float64(8.356209490742065e-05), 'aries': np.float64(8.33051643061177e-05), 'arcc': np.float64(7.786573489912293e-05), 'ara': np.float64(7.53427206929459e-05), 'agms': np.float64(1.2612095468501342e-05), 'amf': np.float64(1.2612095468501342e-05), 'anna': np.float64(1.2612095468501342e-05), 'iva': np.float64(1.2612095468501342e-05)}
A3: =IF(COUNTIF(Topic_importance!$A$2:$A$21,Topic_words!B3),1,0) -> 0 | B3: 1 | C3: {'eur': np.float64(0.9914591731667453), 'crr': np.float64(0.06414105771196568), 'rwa': np.float64(0.06408943440143001), 'organisation': np.float64(0.04371825917436218), 'resource': np.float64(0.04198999359037067), 'apply': np.float64(0.03887716665734515), 'arises': np.float64(0.03135428414600905), 'application': np.float64(0.030402466794047536), 'agency': np.float64(0.027598193198046492), 'approximately': np.float64(0.01454754727860801), 'raf': np.float64(0.011124567183344408), 'srep': np.float64(0.01102671043592442), 'aspect': np.float64(0.009015410502376557), 'user': np.float64(0.007994219251268274), 'apart': np.float64(0.007929984314903153), 'roa': np.float64(0.006824592778412507), 'parp': np.float64(0.006070912196299859), 'payer': np.float64(0.005491325562401901), 'irb': np.float64(0.005350809792994664), 'operative': np.float64(0.0051524366353263695), 'creation': np.float64(0.004636020267849089), 'sharing': np.float64(0.003952368113489293), 'ilaap': np.float64(0.0038242501863995993), 'arab': np.float64(0.0027738704782876078), 'irba': np.float64(0.002704297105178147), 'pace': np.float64(0.002374956572283429), 'approver': np.float64(0.0021457650192293247), 'upstream': np.float64(0.0019458371917519465), 'pit': np.float64(0.0019043879362646895), 'npa': np.float64(0.0017168591573698457), 'cpri': np.float64(0.0016349365636020637), 'ease': np.float64(0.0012681854363663302), 'unep': np.float64(0.0012472165830299798), 'alrb': np.float64(0.0010329904661337088), 'apac': np.float64(0.0007635188044080384), 'acpr': np.float64(0.0007265411870056441), 'rrap': np.float64(0.0006600263377147956), 'emapp': np.float64(0.0006104601842939636), 'appraisal': np.float64(0.0006027081163846997), 'appraiser': np.float64(0.0006027081163846997), 'rata': np.float64(0.0006027081163846997), 'pair': np.float64(0.00047010161157612465), 'tap': np.float64(0.0004253099936007928), 'cope': np.float64(0.00041554140875796526), 'rcp': np.float64(0.0003547962455678136), 'sar': np.float64(0.0002974751336395875), 'apparel': np.float64(0.0002752331201635771), 'ran': np.float64(0.00024891966367087326), 'eafe': np.float64(0.0002401598029076222), 'manu': np.float64(0.00021444245086326674), 'rcuv': np.float64(0.0001838449879830238), 'reappraisal': np.float64(0.0001713340891106298), 'ordination': np.float64(0.00016766565976642135), 'orp': np.float64(0.000126362810387379), 'respon': np.float64(8.279039718632902e-05), 'airplus': np.float64(6.237287377578079e-05), 'andersen': np.float64(6.237287377578079e-05), 'anne': np.float64(6.237287377578079e-05), 'aarup': np.float64(6.23728737757553e-05), 'transac': np.float64(4.031777970256807e-05)}
A4: =IF(COUNTIF(Topic_importance!$A$2:$A$21,Topic_words!B4),1,0) -> 0 | B4: 2 | C4: {'decrease': np.float64(0.47067761219051024), 'adverse': np.float64(0.46130538026830126), 'reduction': np.float64(0.3703793388969188), 'mitigation': np.float64(0.31068842106285577), 'reduced': np.float64(0.2538892497758991), 'reduce': np.float64(0.24945496770397627), 'deduction': np.float64(0.2268582770599077), 'mitigate': np.float64(0.19176053634725151), 'adversely': np.float64(0.15296868567879382), 'forborne': np.float64(0.15152541766181443), 'excludes': np.float64(0.14635381593278526), 'mitigating': np.float64(0.11804810438485892), 'reducing': np.float64(0.09942948055866135), 'avoid': np.float64(0.05943769189061195), 'mitigated': np.float64(0.05662746615529307), 'deducted': np.float64(0.056295557211559114), 'termination': np.float64(0.05458751418440104), 'detriment': np.float64(0.04340039485388868), 'cure': np.float64(0.03912697661289086), 'reduces': np.float64(0.03667683395524951), 'exclude': np.float64(0.03493327301685731), 'removal': np.float64(0.023155750666693547), 'lesser': np.float64(0.023075005412071015), 'cease': np.float64(0.02085478962073308), 'minimize': np.float64(0.020641464675850197), 'terminate': np.float64(0.020527942044195772), 'absorb': np.float64(0.019109686107941833), 'mitigates': np.float64(0.01834499338428045), 'remove': np.float64(0.01691639867032511), 'remediate': np.float64(0.015691244724325443), 'censure': np.float64(0.015466490622379222), 'subdued': np.float64(0.015327330213001283), 'eliminate': np.float64(0.01494989537182707), 'minimising': np.float64(0.013373944204823626), 'ceasing': np.float64(0.01300434104026896), 'minimise': np.float64(0.012935427201890793), 'deviate': np.float64(0.011892590531495592), 'mitigant': np.float64(0.011380465772326704), 'combating': np.float64(0.011362527462384907), 'deducting': np.float64(0.011061587280932397), 'abuse': np.float64(0.010006525906090162), 'shrink': np.float64(0.009436142355733812), 'deminimis': np.float64(0.009234406830394776), 'deduct': np.float64(0.008785635024860898), 'downgraded': np.float64(0.008326589096424772), 'avoids': np.float64(0.0077153351975212895), 'modify': np.float64(0.007654478899881115), 'refine': np.float64(0.007036512283011241), 'reprimand': np.float64(0.007010732684945121), 'precluded': np.float64(0.006254157300424734), 'subtracting': np.float64(0.006254157300424734), 'removing': np.float64(0.006221369666839943), 'inhibit': np.float64(0.00618627503887401), 'omitted': np.float64(0.00618627503887401), 'abrupt': np.float64(0.0060841146483055185), 'eliminated': np.float64(0.00602938735975901), 'diminished': np.float64(0.005117893854818197), 'veto': np.float64(0.004978265616100888), 'deductible': np.float64(0.004914895549669453), 'hampered': np.float64(0.004913333802379312), 'narrowed': np.float64(0.004913333802379312), 'trim': np.float64(0.004910861655682038), 'prohibit': np.float64(0.0047461898285474655), 'elimination': np.float64(0.0035899505031996653), 'abused': np.float64(0.0033605480669442835), 'demise': np.float64(0.003276379917151966), 'suppression': np.float64(0.003276379917151966), 'abate': np.float64(0.003276379917151916), 'receded': np.float64(0.0032719909235112625), 'abolished': np.float64(0.003211187029571014), 'refusing': np.float64(0.0031204531449233663), 'foregoing': np.float64(0.0030939405446312033), 'revocation': np.float64(0.0030939405446312033), 'impair': np.float64(0.003092334494242807), 'abreast': np.float64(0.0024977304306035343), 'revert': np.float64(0.002362211765087035), 'aversion': np.float64(0.0023428081066995373), 'amend': np.float64(0.0022343896216189163), 'cured': np.float64(0.0020724317960000376), 'hinders': np.float64(0.0020724317960000376), 'withdraw': np.float64(0.001773462355433842), 'dampened': np.float64(0.0015567231898314035), 'discontinue': np.float64(0.0014748743478390643), 'abated': np.float64(0.0012669360630776754), 'imputed': np.float64(0.0012669360630776754), 'tapering': np.float64(0.001264541661358488), 'curtailment': np.float64(0.0010600052934018095), 'eliminates': np.float64(0.00089400790407993), 'abovementioned': np.float64(0.0008823574076356776), 'terminated': np.float64(0.0007883250643740518), 'lowering': np.float64(0.0007137339113271697), 'waive': np.float64(0.00038045313062054704), 'ated': np.float64(0.00037718147735961454), 'deter': np.float64(7.619137253714825e-05)}
A5: =IF(COUNTIF(Topic_importance!$A$2:$A$21,Topic_words!B5),1,0) -> 0 | B5: 3 | C5: {'compliance': np.float64(0.6311043999646152), 'must': np.float64(0.3923657150183745), 'ensure': np.float64(0.3597359621537454), 'manage': np.float64(0.31617129681773976), 'continue': np.float64(0.2107868909600736), 'accordance': np.float64(0.18647130150146257), 'remains': np.float64(0.15570306266214406), 'maintain': np.float64(0.14770265438556004), 'require': np.float64(0.11244860161566689), 'remain': np.float64(0.11205713669657308), 'remained': np.float64(0.09622039325596), 'hold': np.float64(0.0958444161558508), 'occur': np.float64(0.08481382597613417), 'comply': np.float64(0.07159256799824912), 'adherence': np.float64(0.07125942942583774), 'yield': np.float64(0.06382536224878423), 'allow': np.float64(0.05310975377331543), 'along': np.float64(0.05168028661938788), 'keep': np.float64(0.04645267358018855), 'compliant': np.float64(0.04644765383361652), 'operate': np.float64(0.04392048681858074), 'consist': np.float64(0.04049735713995693), 'rely': np.float64(0.04008893173864574), 'fulfil': np.float64(0.03804731540941544), 'vary': np.float64(0.03267508389460564), 'governed': np.float64(0.03198739951605373), 'incorporate': np.float64(0.03186360022250658), 'believe': np.float64(0.026825057809638078), 'contain': np.float64(0.025618648343723745), 'exist': np.float64(0.024852321306120067), 'accept': np.float64(0.023080776112365434), 'relies': np.float64(0.021348897900019554), 'withstand': np.float64(0.020707915276514492), 'carry': np.float64(0.01860841246249537), 'govern': np.float64(0.018522134756262097), 'shall': np.float64(0.017974401594517377), 'undertake': np.float64(0.017906162671033104), 'living': np.float64(0.016839012929267237), 'incur': np.float64(0.015640175535830685), 'live': np.float64(0.015033708843827395), 'keeping': np.float64(0.015007963680191319), 'stay': np.float64(0.014993854352219177), 'domiciled': np.float64(0.014407677190389039), 'depend': np.float64(0.013891301009984777), 'fulfill': np.float64(0.013012812212861843), 'adhere': np.float64(0.012603623645244358), 'pursue': np.float64(0.011960885571133258), 'complied': np.float64(0.01077382852321748), 'complies': np.float64(0.010466237190654867), 'settle': np.float64(0.010279111348671474), 'adheres': np.float64(0.010178014596140083), 'standby': np.float64(0.010052523483768817), 'engage': np.float64(0.009932133237364322), 'adhering': np.float64(0.009861690723920806), 'adhered': np.float64(0.009588674868754473), 'enforce': np.float64(0.00942881400974528), 'resides': np.float64(0.009295374361819623), 'belong': np.float64(0.008526867872492539), 'suffer': np.float64(0.008095128615434313), 'encompass': np.float64(0.0069059948389385275), 'participate': np.float64(0.006712249272713697), 'complying': np.float64(0.006522026100186325), 'survive': np.float64(0.006347698238439669), 'happen': np.float64(0.0061760809336308875), 'governs': np.float64(0.005838668422782989), 'belonging': np.float64(0.005762336593004389), 'intend': np.float64(0.005172452620098467), 'undergo': np.float64(0.005011132187253556), 'appear': np.float64(0.004877839889578404), 'conform': np.float64(0.003911475863195357), 'succeed': np.float64(0.0037186244945919193), 'necessitate': np.float64(0.003442274758724776), 'therein': np.float64(0.003334323544735957), 'occupy': np.float64(0.003124603420382634), 'existence': np.float64(0.0030466534084096484), 'dwelling': np.float64(0.0030462252943274804), 'presence': np.float64(0.00282972725577944), 'belongs': np.float64(0.0025883485012879854), 'relying': np.float64(0.0025883485012879854), 'substantiate': np.float64(0.0025883485012879854), 'persisted': np.float64(0.002460225960939526), 'sit': np.float64(0.0024056909950420477), 'cooperate': np.float64(0.0023111406108184715), 'navigate': np.float64(0.001871169201184627), 'persist': np.float64(0.0018626305484536415), 'observe': np.float64(0.0018366206330595292), 'habit': np.float64(0.0017873208407753708), 'staying': np.float64(0.0016591983004269107), 'embrace': np.float64(0.0016092901666155174), 'persists': np.float64(0.0014780266209467256), 'refrain': np.float64(0.0014140203407781646), 'proceed': np.float64(0.000929080877690761), 'abide': np.float64(0.0009162078285748468), 'pliance': np.float64(0.0008891182655177012), 'pertains': np.float64(0.0007758792139681591), 'sustain': np.float64(0.0007715554513099426), 'prevail': np.float64(0.0006612496808461714), 'attend': np.float64(0.00013759776482587285)}
A6: =IF(COUNTIF(Topic_importance!$A$2:$A$21,Topic_words!B6),1,0) -> 0 | B6: 4 | C6: {'liability': np.float64(0.7088166659864291), 'impairment': np.float64(0.39380837816378256), 'potential': np.float64(0.3880763633330819), 'responsibility': np.float64(0.20448260825835696), 'available': np.float64(0.19654323789104675), 'adequacy': np.float64(0.14554862667830637), 'ability': np.float64(0.13497695896036577), 'facility': np.float64(0.11312133846930353), 'provided': np.float64(0.11229614124755845), 'capacity': np.float64(0.09881213394660496), 'access': np.float64(0.07776465349260403), 'power': np.float64(0.04799077892657929), 'allocated': np.float64(0.04729526746792276), 'active': np.float64(0.04608429084275007), 'requires': np.float64(0.04330757924568559), 'allocation': np.float64(0.04199224148831205), 'enable': np.float64(0.039258738560596085), 'able': np.float64(0.038808446213274804), 'vulnerability': np.float64(0.035746376183133664), 'capability': np.float64(0.03542881937185697), 'enables': np.float64(0.03375621651094137), 'utility': np.float64(0.033235341194421945), 'dependent': np.float64(0.03265405786872641), 'opportunity': np.float64(0.031537425817183676), 'difficulty': np.float64(0.03073384309440717), 'affordability': np.float64(0.030387573530051313), 'availability': np.float64(0.029602656967303156), 'inclusion': np.float64(0.027833472376179162), 'anticipated': np.float64(0.027414618987596392), 'unable': np.float64(0.02726453049904795), 'awareness': np.float64(0.02593139210799463), 'allows': np.float64(0.025626331219950272), 'limitation': np.float64(0.025340355497626307), 'inability': np.float64(0.023066162665734195), 'advanced': np.float64(0.01971645990465297), 'willing': np.float64(0.019685235733752575), 'encumbered': np.float64(0.017891511331985438), 'allowing': np.float64(0.014976014914176295), 'readily': np.float64(0.013796353267566144), 'competence': np.float64(0.013296523673196128), 'eligibility': np.float64(0.013109000697186967), 'facilitation': np.float64(0.012420180880935156), 'unavailability': np.float64(0.012117747283593836), 'allowed': np.float64(0.010749113033588859), 'liable': np.float64(0.009201119701382862), 'equipment': np.float64(0.008850996836501352), 'enabling': np.float64(0.0081802141941562), 'permitted': np.float64(0.007850942409133574), 'enabled': np.float64(0.007489771389843525), 'skill': np.float64(0.007013939701113597), 'possibility': np.float64(0.006877327755846327), 'recoverability': np.float64(0.006874872937725532), 'authorized': np.float64(0.006617837867821928), 'authorization': np.float64(0.0065226774761210585), 'ment': np.float64(0.00625804691374239), 'reliant': np.float64(0.006166413917008858), 'optionality': np.float64(0.005091164788563524), 'permission': np.float64(0.004897194680778629), 'flexibility': np.float64(0.004554601065870277), 'readiness': np.float64(0.003950110780194624), 'preparedness': np.float64(0.003672819509429227), 'adapting': np.float64(0.0034288352917405287), 'compatible': np.float64(0.0032749277054630486), 'achievement': np.float64(0.0031963693891816176), 'responsiveness': np.float64(0.0031252114726296374), 'disability': np.float64(0.0028403523771299635), 'mobility': np.float64(0.002727334431564875), 'accessible': np.float64(0.002512267549761437), 'impairmentc': np.float64(0.0021164802185886103), 'functionality': np.float64(0.001998151079165305), 'movable': np.float64(0.001904405161049246), 'willingness': np.float64(0.0015821549144818207), 'optionalities': np.float64(0.0015578613664559964), 'adapts': np.float64(0.001426993779043838), 'allowancec': np.float64(0.0014074575678996765), 'attachment': np.float64(0.001401209544212319), 'accommodative': np.float64(0.0013968698344214857), 'ance': np.float64(0.000554865873173674), 'incapacity': np.float64(0.0005289194254446171), 'usability': np.float64(0.0005010041496195421), 'ity': np.float64(0.0004405134657826338), 'resiliency': np.float64(0.0003656125243857103), 'capable': np.float64(0.0003623009556145751), 'compatibility': np.float64(0.00036191804223810307), 'competency': np.float64(0.0003392265678085397), 'sibility': np.float64(0.0003152252467348095), 'ency': np.float64(0.00014888734167010868), 'tainability': np.float64(0.00012371230980545337)}
A7: =IF(COUNTIF(Topic_importance!$A$2:$A$21,Topic_words!B7),1,0) -> 0 | B7: 5 | C7: {'foreign': np.float64(0.7330194967679592), 'different': np.float64(0.41367949649648666), 'negative': np.float64(0.3451272637819334), 'impaired': np.float64(0.2797691355548942), 'elevated': np.float64(0.13510900315252686), 'beyond': np.float64(0.11446969055917629), 'extreme': np.float64(0.11313435257483002), 'normal': np.float64(0.09368669822258421), 'excess': np.float64(0.09225277332018679), 'wrong': np.float64(0.0836334253295862), 'excluded': np.float64(0.061174014453666554), 'inadequate': np.float64(0.05823008873001022), 'deviation': np.float64(0.049805878045952816), 'exceeding': np.float64(0.04731683430805092), 'outlier': np.float64(0.04621050283017248), 'ordinary': np.float64(0.04328110636585845), 'exceptional': np.float64(0.0314707162813453), 'undue': np.float64(0.03023466480453572), 'inappropriate': np.float64(0.029716827745149835), 'exceed': np.float64(0.02811838386789387), 'artificial': np.float64(0.02581540251136979), 'exceeded': np.float64(0.02516572950394151), 'malicious': np.float64(0.023016254761040963), 'unauthorised': np.float64(0.022900548897308484), 'illegal': np.float64(0.021173446590731452), 'excessive': np.float64(0.01875155630907128), 'usual': np.float64(0.01808997065193815), 'illicit': np.float64(0.01543999925135399), 'unacceptable': np.float64(0.01451700319185643), 'unfavourable': np.float64(0.01390535248125257), 'asymmetry': np.float64(0.013473780295349768), 'disrupted': np.float64(0.012662032090204063), 'substandard': np.float64(0.011840977649238887), 'ordinarily': np.float64(0.011184042369654874), 'disorderly': np.float64(0.01112633137653183), 'harmful': np.float64(0.010549229116716257), 'unauthorized': np.float64(0.01051256708705017), 'disruptive': np.float64(0.009710519391348897), 'suspicious': np.float64(0.009163954482399365), 'undesired': np.float64(0.008939185442095156), 'unethical': np.float64(0.008758096654920283), 'unprecedented': np.float64(0.00817078884478759), 'bad': np.float64(0.007836492011534156), 'benign': np.float64(0.007281739337723294), 'flaw': np.float64(0.007156032358750566), 'improper': np.float64(0.0064784753857103266), 'unsuitable': np.float64(0.006356061521130801), 'improperly': np.float64(0.006269014386185159), 'unintended': np.float64(0.006133318077803893), 'abroad': np.float64(0.005754873185230771), 'biased': np.float64(0.005692158987590984), 'unusual': np.float64(0.005364822833396014), 'deviating': np.float64(0.0052857444350306254), 'normally': np.float64(0.005215147207532334), 'undesirable': np.float64(0.005172463326220543), 'unstable': np.float64(0.004977277918600003), 'erroneous': np.float64(0.0041675540142454785), 'erroneously': np.float64(0.0041675540142454785), 'illegally': np.float64(0.0041675540142454785), 'inappropriately': np.float64(0.004123717481025961), 'exogenous': np.float64(0.004003559312410655), 'extraordinary': np.float64(0.00399629338364221), 'inaccurate': np.float64(0.003995371997255412), 'lacking': np.float64(0.003995371997255412), 'unfairly': np.float64(0.0038833822803892295), 'flawed': np.float64(0.0033458294555682193), 'impropriety': np.float64(0.0032392376928551633), 'altered': np.float64(0.0031489733153419372), 'unduly': np.float64(0.003116823828275638), 'contrary': np.float64(0.003059339025594919), 'skewed': np.float64(0.0029884783445050895), 'unaltered': np.float64(0.0029884783445050895), 'unlawfully': np.float64(0.0029884783445050895), 'unforeseen': np.float64(0.0029044312762115834), 'exceptionally': np.float64(0.002497587259713162), 'turbulent': np.float64(0.002470674165953379), 'damaged': np.float64(0.002198298152756987), 'sick': np.float64(0.002188507506885322), 'unconventional': np.float64(0.001983569032530022), 'unlawful': np.float64(0.0019815846917547644), 'unfavorable': np.float64(0.001965764063558415), 'fraudulent': np.float64(0.0019476916528201804), 'sickness': np.float64(0.0018604540903243657), 'unfair': np.float64(0.0015216567513542235), 'altering': np.float64(0.001420563478822999), 'unfavourably': np.float64(0.0014092958945540715), 'toxic': np.float64(0.001195373181557179), 'overly': np.float64(0.0011891062723310255), 'unnecessary': np.float64(0.000524101742426516), 'disturbed': np.float64(0.00045324106133668525), 'unpredicted': np.float64(0.00045324106133668525), 'abnormal': np.float64(0.00042280582571431295), 'uncontrolled': np.float64(0.0003977162962578704), 'rare': np.float64(0.00031486497497550076), 'unexpect': np.float64(0.0001593700474676321)}
A8: =IF(COUNTIF(Topic_importance!$A$2:$A$21,Topic_words!B8),1,0) -> 1 | B8: 6 | C8: {'loss': np.float64(0.9879601824892313), 'excluding': np.float64(0.12850249192443003), 'without': np.float64(0.03798804483524881), 'exemption': np.float64(0.036783936668929054), 'gap': np.float64(0.03166056400394097), 'except': np.float64(0.029619778488020283), 'shortfall': np.float64(0.02795411606723868), 'insufficient': np.float64(0.01810009832378802), 'weakness': np.float64(0.016869250572411187), 'negatively': np.float64(0.014615312510228917), 'deficiency': np.float64(0.01322378562835407), 'lack': np.float64(0.01175460065594728), 'cancellation': np.float64(0.009645018309528814), 'delinquency': np.float64(0.008903375982976202), 'expired': np.float64(0.008613970882240132), 'missing': np.float64(0.007806247734769052), 'withdrawal': np.float64(0.007212449189483454), 'absence': np.float64(0.006826869791420281), 'withdrawn': np.float64(0.006382459038457069), 'evasion': np.float64(0.006020041919542994), 'avoiding': np.float64(0.005471835150793179), 'deficit': np.float64(0.0054502801076992576), 'exclusion': np.float64(0.005075211138771163), 'leaving': np.float64(0.004936612372756857), 'unavailable': np.float64(0.004508457008524348), 'cessation': np.float64(0.004480601372612719), 'ineffectiveness': np.float64(0.004236342664235114), 'absorption': np.float64(0.00418755209779027), 'shortcoming': np.float64(0.004161790777234578), 'fails': np.float64(0.003929277712092206), 'discontinuation': np.float64(0.003743835863730701), 'outage': np.float64(0.003485322765502691), 'shortage': np.float64(0.0034669593272569424), 'inaction': np.float64(0.003200210016181436), 'suspension': np.float64(0.00317928681229051), 'vacancy': np.float64(0.002683661132802587), 'away': np.float64(0.0026831443685401456), 'interruption': np.float64(0.002640030676482481), 'none': np.float64(0.002452001074220664), 'immateriality': np.float64(0.002093776048895135), 'possession': np.float64(0.002093776048895135), 'leakage': np.float64(0.001933034489934879), 'lapse': np.float64(0.0017712664196054355), 'vacant': np.float64(0.0016786367478132018), 'depletion': np.float64(0.001534230466290734), 'null': np.float64(0.0014949895656201804), 'separation': np.float64(0.0014829877673478815), 'dismissal': np.float64(0.001346105882983001), 'illness': np.float64(0.0013132405295483447), 'avoidance': np.float64(0.0012024757433311726), 'ineffectivenes': np.float64(0.0011959916524961441), 'incomplete': np.float64(0.0011709535458185754), 'inaccessibility': np.float64(0.0010019243664332583), 'omission': np.float64(0.0009545282500923268), 'inactive': np.float64(0.0008969937393721083), 'departure': np.float64(0.0007681763122789931), 'missed': np.float64(0.0007681763122789931), 'furlough': np.float64(0.0006376797555076705), 'scarcity': np.float64(0.0005721012652577448), 'attendance': np.float64(0.0005049774927893446), 'inaccessible': np.float64(0.00046504278192815177), 'avoided': np.float64(0.0003152285970809311), 'withholding': np.float64(0.00020873734544378796)}
A9: =IF(COUNTIF(Topic_importance!$A$2:$A$21,Topic_words!B9),1,0) -> 1 | B9: 7 | C9: {'total': np.float64(0.651151716978602), 'value': np.float64(0.6090299604821936), 'amount': np.float64(0.2677165993534033), 'basis': np.float64(0.17714898572731008), 'defined': np.float64(0.13973946314217395), 'quality': np.float64(0.13928468666199575), 'significant': np.float64(0.13073691258686726), 'real': np.float64(0.1268435704984402), 'overall': np.float64(0.07697912666826644), 'physical': np.float64(0.06375033441689762), 'maximum': np.float64(0.05656158255306666), 'amounting': np.float64(0.05060408755815463), 'definition': np.float64(0.045753695335661926), 'full': np.float64(0.03785039857764906), 'base': np.float64(0.03580537420263622), 'actual': np.float64(0.03509922131915546), 'consistent': np.float64(0.03475645651628307), 'relative': np.float64(0.03334824003264418), 'final': np.float64(0.02894640752317672), 'major': np.float64(0.02601511828725262), 'fixed': np.float64(0.025293847688818778), 'zero': np.float64(0.024505744992191915), 'mean': np.float64(0.022448677861344066), 'severity': np.float64(0.01734406390982274), 'recognized': np.float64(0.017123672337408732), 'highest': np.float64(0.015079048159282371), 'greater': np.float64(0.013812508924492038), 'equal': np.float64(0.013617537643301326), 'integral': np.float64(0.011634591505751517), 'whole': np.float64(0.01125444871755929), 'best': np.float64(0.011121075477480712), 'absolute': np.float64(0.009082772457522002), 'sum': np.float64(0.008749316597838694), 'plus': np.float64(0.00855654520366087), 'degree': np.float64(0.008189730969722682), 'constant': np.float64(0.007852917469941592), 'essential': np.float64(0.007590184803549388), 'accepted': np.float64(0.0075576860011875345), 'accuracy': np.float64(0.007340625698371838), 'acceptable': np.float64(0.007165546828366629), 'complete': np.float64(0.006749475877515703), 'fundamental': np.float64(0.006585013649671509), 'prime': np.float64(0.005816943542755235), 'valid': np.float64(0.005606714629497112), 'distinct': np.float64(0.004936015603215158), 'completeness': np.float64(0.004283904632118121), 'exists': np.float64(0.004163908399161203), 'explicit': np.float64(0.0039693133334206725), 'uniform': np.float64(0.003866040642031797), 'ultimate': np.float64(0.0038367029515854927), 'virtual': np.float64(0.0036032268823730663), 'supreme': np.float64(0.003503595181227297), 'entire': np.float64(0.003423775765852932), 'proper': np.float64(0.003326294886541977), 'equating': np.float64(0.0031981394894352254), 'implicit': np.float64(0.0030981412519768456), 'qualification': np.float64(0.0029238212803339024), 'certainty': np.float64(0.0026227751832862425), 'almost': np.float64(0.0025320618714931267), 'permanent': np.float64(0.002418447884065639), 'lasting': np.float64(0.0020672726299544877), 'implicitly': np.float64(0.0019644853373804454), 'max': np.float64(0.001962377587759017), 'inclusive': np.float64(0.0018801686630876486), 'true': np.float64(0.0016381676396175907), 'completely': np.float64(0.0015788484140965892), 'norm': np.float64(0.0012672102265180402), 'perfect': np.float64(0.0011404007720731942), 'bound': np.float64(0.0011325053426768372), 'assert': np.float64(0.0011256320988675928), 'entirety': np.float64(0.0010829975605525569), 'inevitable': np.float64(0.0010057565358999893), 'basic': np.float64(0.0009197018139873969), 'totaling': np.float64(0.0008785356133971603), 'ever': np.float64(0.0008596003274843389), 'unconditionally': np.float64(0.0006592871319136481), 'exactly': np.float64(0.0006213008495722866), 'normalized': np.float64(0.0005696858857517491), 'invalid': np.float64(0.00047663920284509245), 'pure': np.float64(0.0004384249509385842), 'invalidate': np.float64(0.0003844556863277021), 'ness': np.float64(0.0003374589302320105), 'universal': np.float64(0.00030708479591184224), 'anything': np.float64(0.00027496359644127666), 'utmost': np.float64(0.0001988932090428639), 'totalling': np.float64(0.00010653059241917647), 'purely': np.float64(7.490398882599659e-05)}
A10: =IF(COUNTIF(Topic_importance!$A$2:$A$21,Topic_words!B10),1,0) -> 0 | B10: 8 | C10: {'applicable': np.float64(0.5792393313529098), 'managing': np.float64(0.4431176771879983), 'taking': np.float64(0.41671028614480665), 'reflected': np.float64(0.2470337160092208), 'reflects': np.float64(0.21720038454604698), 'acquisition': np.float64(0.20313221921819602), 'applying': np.float64(0.16080332332459524), 'reflecting': np.float64(0.15087014700970228), 'supporting': np.float64(0.11504630890458181), 'captured': np.float64(0.10644115907582197), 'affecting': np.float64(0.10021164679069945), 'implementing': np.float64(0.0992508168235479), 'retained': np.float64(0.09697038406725415), 'assumed': np.float64(0.0927609004064492), 'understanding': np.float64(0.07401889331014617), 'absorbing': np.float64(0.06572554321720023), 'impacting': np.float64(0.06334003308451981), 'focusing': np.float64(0.06052881737094532), 'requiring': np.float64(0.055390197770854764), 'growing': np.float64(0.04650559507631039), 'maturing': np.float64(0.03970207759361074), 'involving': np.float64(0.03390672759337842), 'incorporating': np.float64(0.029106948113800078), 'approving': np.float64(0.02898646495985515), 'becoming': np.float64(0.028548838435804035), 'deriving': np.float64(0.027517621046334484), 'capturing': np.float64(0.026867266812142795), 'aggregating': np.float64(0.023987989083969083), 'integrating': np.float64(0.021545439652302798), 'contributing': np.float64(0.021011685092336214), 'adding': np.float64(0.017095256179434505), 'engaging': np.float64(0.01690284841307919), 'expanding': np.float64(0.015346343089329159), 'encompassing': np.float64(0.015313974018146988), 'earning': np.float64(0.014959218152266035), 'recognising': np.float64(0.01247710293507874), 'gained': np.float64(0.012113092639796413), 'incurring': np.float64(0.01168302329371194), 'participating': np.float64(0.011147682612413192), 'responding': np.float64(0.010731264608036955), 'obtaining': np.float64(0.010596044887424163), 'collecting': np.float64(0.008736985997628005), 'consolidating': np.float64(0.008626712091291962), 'reflective': np.float64(0.008613363570015622), 'retaining': np.float64(0.008593053772069776), 'recognizing': np.float64(0.008477701841166361), 'acquires': np.float64(0.007523002305115337), 'fulfilling': np.float64(0.006886700895499125), 'acquire': np.float64(0.006631927497786615), 'pertaining': np.float64(0.006509551932817706), 'recovering': np.float64(0.006222904642937807), 'containing': np.float64(0.006094048562067822), 'accepting': np.float64(0.005760859871525549), 'accrue': np.float64(0.004805524060972541), 'observing': np.float64(0.004271674749819575), 'accelerating': np.float64(0.004157068757126201), 'passing': np.float64(0.004126896032712663), 'affirming': np.float64(0.003995784810544702), 'collapsing': np.float64(0.003942173469874823), 'emitting': np.float64(0.0038478095749557685), 'attracting': np.float64(0.0038322574403021076), 'employing': np.float64(0.0038322574403021076), 'benefiting': np.float64(0.0038245742244357307), 'consuming': np.float64(0.003698428080679606), 'demanding': np.float64(0.003491215222973518), 'knowing': np.float64(0.003491215222973518), 'repaying': np.float64(0.003491215222973518), 'adjusting': np.float64(0.003487026718322217), 'getting': np.float64(0.0034122549559151252), 'effecting': np.float64(0.003291367381777467), 'fading': np.float64(0.003089933517403928), 'shrinking': np.float64(0.0027562724917687075), 'acknowledging': np.float64(0.002750077204869559), 'accumulation': np.float64(0.0024654521961696334), 'focussing': np.float64(0.002311686935577308), 'occupying': np.float64(0.0022819509902577938), 'paying': np.float64(0.0018889081397908398), 'appreciating': np.float64(0.0013272514542067672), 'ecting': np.float64(0.0013262435649263088), 'acquiring': np.float64(0.0012609862559568163), 'realising': np.float64(0.0011270806878520042), 'adopting': np.float64(0.001055221241939867), 'emphasising': np.float64(0.0008445725038144858), 'amortising': np.float64(0.0006497054374452745), 'embracing': np.float64(0.0005291728618803057)}
A11: =IF(COUNTIF(Topic_importance!$A$2:$A$21,Topic_words!B11),1,0) -> 0 | B11: 9 | C11: {'transaction': np.float64(0.7185588080435882), 'legal': np.float64(0.63103742385366), 'contract': np.float64(0.17787531605496298), 'disposal': np.float64(0.1192841903043854), 'execution': np.float64(0.10769938192742647), 'solvency': np.float64(0.07989423529510739), 'irrevocable': np.float64(0.07673913102375209), 'revocable': np.float64(0.06562375435222742), 'liquidation': np.float64(0.05887726405416587), 'legally': np.float64(0.04694251960153867), 'finma': np.float64(0.03779583055457031), 'closing': np.float64(0.03344676621121604), 'derecognition': np.float64(0.031017070939517638), 'legislation': np.float64(0.028954383798541084), 'closure': np.float64(0.018203360287943803), 'bankruptcy': np.float64(0.015698951371249888), 'completion': np.float64(0.011563242973431928), 'insolvency': np.float64(0.009414696899453132), 'liquidated': np.float64(0.009382308660144379), 'contractually': np.float64(0.008411167400933103), 'ceased': np.float64(0.008147609010093596), 'bundesbank': np.float64(0.008105280009094658), 'amortisation': np.float64(0.0056309883508399855), 'restructurings': np.float64(0.005606476317267224), 'ending': np.float64(0.005253134364283806), 'liquidate': np.float64(0.005173133969689062), 'cancelled': np.float64(0.005062012488232943), 'transacting': np.float64(0.0041944242207475), 'abwicklungsgesetz': np.float64(0.004052640004547345), 'bundesanstalt': np.float64(0.004052640004547329), 'discontinuance': np.float64(0.004052640004547329), 'elapses': np.float64(0.004052640004547329), 'finanzdienstleistungsaufsicht': np.float64(0.004052640004547329), 'kreditwesengesetz': np.float64(0.004052640004547329), 'liquidating': np.float64(0.004052640004547329), 'sanierungs': np.float64(0.004052640004547329), 'rescission': np.float64(0.002413558850109942), 'cassation': np.float64(0.0017103776787805772), 'severance': np.float64(0.0017103776787805772), 'finalization': np.float64(0.0016394475413681051), 'finalisation': np.float64(0.001356865596546579), 'gmbh': np.float64(0.0011402517858537181), 'regula': np.float64(0.000797168688817731), 'verwaltungs': np.float64(0.0001243049186946448), 'terminating': np.float64(8.246601051990132e-05)}
A12: =IF(COUNTIF(Topic_importance!$A$2:$A$21,Topic_words!B12),1,0) -> 1 | B12: 10 | C12: {'credit': np.float64(0.7203035704564746), 'capital': np.float64(0.6210478282745419), 'based': np.float64(0.18440352352795059), 'internal': np.float64(0.15166078754310905), 'assessment': np.float64(0.08747174457081451), 'subject': np.float64(0.08293232417110541), 'profile': np.float64(0.07787412970837579), 'institution': np.float64(0.05007458891816011), 'senior': np.float64(0.04940433737689873), 'authority': np.float64(0.04130955704316903), 'associated': np.float64(0.04061437383273759), 'eligible': np.float64(0.03901418994941375), 'valuation': np.float64(0.03549373342437223), 'principal': np.float64(0.032807540404646625), 'finance': np.float64(0.03206060445733831), 'approved': np.float64(0.03180760773267783), 'personal': np.float64(0.028182690289913374), 'grade': np.float64(0.027830558200402575), 'expert': np.float64(0.018066372274851465), 'structural': np.float64(0.017775232468124222), 'primary': np.float64(0.014819296066196566), 'audit': np.float64(0.014552179542287096), 'benchmark': np.float64(0.01254726925865029), 'master': np.float64(0.012362498590282166), 'published': np.float64(0.011811234471410722), 'professional': np.float64(0.009399506807918487), 'training': np.float64(0.009327981239636777), 'critical': np.float64(0.0087771511078265), 'premium': np.float64(0.0071155366172057375), 'national': np.float64(0.0062991138458836984), 'education': np.float64(0.004872386149347923), 'completed': np.float64(0.004869512527807492), 'political': np.float64(0.004774084633315698), 'scientific': np.float64(0.004677735130114897), 'learning': np.float64(0.00458407119261388), 'learned': np.float64(0.004502484010060915), 'course': np.float64(0.004481520165574054), 'evaluation': np.float64(0.0042392522967681905), 'validated': np.float64(0.0034214589039332755), 'certificate': np.float64(0.0027785822929546396), 'civil': np.float64(0.0020169965022122), 'history': np.float64(0.001905753201020907), 'qualified': np.float64(0.00184247989388481), 'associate': np.float64(0.001811822799133718), 'formal': np.float64(0.001595335171623751), 'secondary': np.float64(0.0015563177725166195), 'background': np.float64(0.0015558987260950688), 'bridge': np.float64(0.0015230492080038746), 'engineering': np.float64(0.0014161519482965746), 'appointed': np.float64(0.0013742029159023834), 'analytics': np.float64(0.001318818004372099), 'credential': np.float64(0.001188032803613249), 'study': np.float64(0.0007094967362463684), 'journal': np.float64(0.0007002656750596502), 'disciplinary': np.float64(0.0006782947482727352), 'career': np.float64(0.0006200979072267092), 'adult': np.float64(0.0005693223602825171), 'academy': np.float64(0.0005659856010221283), 'award': np.float64(0.0004906468945020271), 'university': np.float64(0.0004894090868694406), 'academic': np.float64(0.00046281531069594444), 'medical': np.float64(0.0004436470215324885), 'resume': np.float64(0.0003807349735032376), 'architecture': np.float64(0.000356380591086717), 'exam': np.float64(0.00033946017149698413), 'graduate': np.float64(0.00033702492756686333), 'school': np.float64(0.00029538393376418785), 'curriculum': np.float64(0.00027742565438499225), 'prof': np.float64(0.00014199437448452726), 'english': np.float64(0.00010640032766449662), 'educational': np.float64(9.710843131541499e-05), 'strate': np.float64(7.218018900362069e-05), 'accreditation': np.float64(7.149273232851826e-05), 'credited': np.float64(5.873631407063797e-05), 'american': np.float64(5.869376848825579e-05), 'cred': np.float64(4.7339091192020225e-05)}
A13: =IF(COUNTIF(Topic_importance!$A$2:$A$21,Topic_words!B13),1,0) -> 0 | B13: 11 | C13: {'increase': np.float64(0.6100479595450934), 'leverage': np.float64(0.4490588143183665), 'driven': np.float64(0.40778928765524697), 'advance': np.float64(0.3386937419773019), 'provide': np.float64(0.22098942816715894), 'driver': np.float64(0.14572675121501266), 'forward': np.float64(0.14267937446690512), 'increasing': np.float64(0.10905260695390802), 'enhanced': np.float64(0.08611019294250606), 'attack': np.float64(0.07259234788086437), 'add': np.float64(0.06146725291789239), 'gain': np.float64(0.05999703399695171), 'improve': np.float64(0.051925971836615306), 'achieve': np.float64(0.048358747345370746), 'develop': np.float64(0.046501965994371355), 'enhance': np.float64(0.04544795004870953), 'progress': np.float64(0.03995443715527757), 'drive': np.float64(0.03894635096816444), 'facilitate': np.float64(0.03658798173960615), 'move': np.float64(0.03450622807245219), 'promote': np.float64(0.033113289312258085), 'generate': np.float64(0.032713490248479915), 'strengthen': np.float64(0.0269403084412979), 'escalated': np.float64(0.026281455058695048), 'adapt': np.float64(0.0184087901982204), 'contribute': np.float64(0.018263558533887433), 'exacerbated': np.float64(0.017945153363480473), 'accelerate': np.float64(0.01771538130132947), 'escalate': np.float64(0.017705451624892444), 'enhancing': np.float64(0.016530918080451887), 'steer': np.float64(0.014741874079377134), 'slowdown': np.float64(0.014328375521079849), 'facilitates': np.float64(0.013879497054764165), 'escalating': np.float64(0.012808796296149175), 'facilitating': np.float64(0.011729090633266282), 'expand': np.float64(0.011472916797425571), 'escalates': np.float64(0.011442755212872701), 'ramped': np.float64(0.01027312412056355), 'promotes': np.float64(0.010179868637230909), 'speed': np.float64(0.010074323030331988), 'grow': np.float64(0.01006584310036815), 'rapid': np.float64(0.010052559337261536), 'quickly': np.float64(0.009772213629470944), 'charged': np.float64(0.009274838288408268), 'accelerated': np.float64(0.008412604271110681), 'advancement': np.float64(0.0074716931711884885), 'rapidly': np.float64(0.007413260335621253), 'reinforce': np.float64(0.0069099699522163814), 'empower': np.float64(0.005719548507335514), 'enhances': np.float64(0.005415795274107068), 'swiftly': np.float64(0.005101315060695561), 'prioritise': np.float64(0.005091499709820595), 'acceleration': np.float64(0.004620150032623686), 'transform': np.float64(0.004475827244195684), 'intensified': np.float64(0.004183859340140619), 'ahead': np.float64(0.004101909397507517), 'fast': np.float64(0.0036519002475379897), 'tighten': np.float64(0.0035822866994218616), 'widen': np.float64(0.0035419483466428404), 'emphasise': np.float64(0.0031745278241473987), 'heighten': np.float64(0.0031745278241473987), 'motivate': np.float64(0.0031745278241473987), 'convey': np.float64(0.0029588654465686343), 'velocity': np.float64(0.0019747011770477395), 'stimulate': np.float64(0.0018888611016791871), 'faster': np.float64(0.0018824402223310119), 'initiate': np.float64(0.0018404428521124076), 'encourage': np.float64(0.0016830859110765007), 'mover': np.float64(0.0016274471311501179), 'intensify': np.float64(0.0015903140213435773), 'leap': np.float64(0.0015903140213435773), 'pressurise': np.float64(0.0015842138028038207), 'drove': np.float64(0.0014392970116372224), 'endorse': np.float64(0.0013365786874213316), 'consolidate': np.float64(0.0013067941573479762), 'automate': np.float64(0.001262139817685506), 'boost': np.float64(0.0011216231406388337), 'swift': np.float64(0.00103085581647153), 'broaden': np.float64(0.001026380406204212), 'maximize': np.float64(0.001026380406204212), 'amplify': np.float64(0.0009475031014317422), 'encouraged': np.float64(0.0008435887811120847), 'aggravating': np.float64(0.0007230528961132119), 'converge': np.float64(0.0007230528961132119), 'exponentially': np.float64(0.0005745251972768772), 'prioritize': np.float64(0.0005745251972768772), 'fuelled': np.float64(0.0005555015627719654), 'lengthens': np.float64(0.0003551986941851827), 'incentivise': np.float64(0.00017935717773441898), 'incre': np.float64(0.00016977083448454608)}
... A254: =IF(COUNTIF(Topic_importance!$A$2:$A$21,Topic_words!B254),1,0) -> 0 | B254: 355 | C254: {'seudun': np.float64(1.0), 'signhild': np.float64(0.0), 'sira': np.float64(0.0), 'skullman': np.float64(0.0), 'sufﬁ': np.float64(0.0)}

Sheet Topic_importance
A1: cluster | B1: leading_importance | C1: second_importance
A2: 14 | B2: 1.7957497e+08
A3: 10 | B3: 23142278
A4: 25 | B4: 13746069
A5: 32 | B5: 9880564
A6: 35 | B6: 6788664.7
A7: 7 | B7: 6454535.3
A8: 23 | B8: 6279779.1
A9: 0 | B9: 5858059.4
A10: 220 | B10: 5313909.3
A11: 97 | B11: 4228037.3
A12: 40 | B12: 3459490.8
A13: 76 | B13: 2743987.8
... A21: 72 | B21: 1665591.1

Sheet Tactor Loading
G1: Risk
B2: document | C2: 0 | D2: 6 | E2: 7 | F2: 10 | G2: 14 | H2: 20 | I2: 23 | J2: 25 | K2: 32 | L2: 35 | M2: 40 | N2: 72 | O2: 74 | P2: 75 | Q2: 76 | R2: 95 | S2: 96 | T2: 97 | U2: 112 | V2: 220
B3: 0 | C3: 51.851002 | D3: 16.256712 | E3: 26.384739 | F3: 97.208034 | G3: 375.03324 | H3: 28.261021 | I3: 23.329239 | J3: 30.386693 | K3: 75.952829 | L3: 22.886214 | M3: 28.733223 | N3: 17.242799 | O3: 42.757097 | P3: 12.80601 | Q3: 15.318453 | R3: 7.4221752 | S3: 14.408651 | T3: 60.968428 | U3: 6.0823417 | V3: 28.920885
B4: 1 | C4: 306.08778 | D4: 82.448464 | E4: 274.51616 | F4: 415.05036 | G4: 1255.2543 | H4: 166.87932 | I4: 257.69948 | J4: 433.84638 | K4: 246.61223 | L4: 306.86222 | M4: 239.22045 | N4: 132.38438 | O4: 171.19988 | P4: 169.65558 | Q4: 233.98395 | R4: 18.442321 | S4: 122.63486 | T4: 203.92765 | U4: 331.30013 | V4: 254.23359
B5: 2 | C5: 89.593904 | D5: 80.369672 | E5: 88.613177 | F5: 158.68255 | G5: 376.95829 | H5: 28.346466 | I5: 106.97509 | J5: 65.232164 | K5: 81.955509 | L5: 155.31725 | M5: 56.668944 | N5: 19.647866 | O5: 45.323145 | P5: 32.056812 | Q5: 49.996293 | R5: 65.084435 | S5: 42.538984 | T5: 81.452215 | U5: 65.454006 | V5: 159.5635
B6: 3 | C6: 430.80043 | D6: 289.38459 | E6: 458.13041 | F6: 893.64199 | G6: 1775.6668 | H6: 185.60125 | I6: 300.2922 | J6: 327.92901 | K6: 447.34327 | L6: 373.00803 | M6: 263.04018 | N6: 91.354876 | O6: 216.61521 | P6: 248.512 | Q6: 228.44635 | R6: 304.19681 | S6: 151.64575 | T6: 285.88389 | U6: 158.61524 | V6: 321.45353
B7: 4 | C7: 173.07534 | D7: 104.89638 | E7: 218.6769 | F7: 312.66391 | G7: 1516.8056 | H7: 145.67565 | I7: 346.13357 | J7: 572.00817 | K7: 467.65299 | L7: 230.21074 | M7: 193.62484 | N7: 172.24455 | O7: 86.66805 | P7: 88.673098 | Q7: 111.47116 | R7: 164.15151 | S7: 158.4752 | T7: 228.24771 | U7: 107.82253 | V7: 106.67224
B8: 5 | C8: 36.46027 | D8: 20.030444 | E8: 32.701488 | F8: 141.92388 | G8: 573.86784 | H8: 20.934039 | I8: 98.002564 | J8: 226.7084 | K8: 202.14597 | L8: 71.353702 | M8: 45.739766 | N8: 32.321705 | O8: 114.97004 | P8: 56.683411 | Q8: 38.282646 | R8: 17.092669 | S8: 33.704955 | T8: 45.806265 | U8: 35.221286 | V8: 27.925506
B9: 6 | C9: 28.571858 | D9: 22.089062 | E9: 23.485592 | F9: 56.268777 | G9: 119.11851 | H9: 12.384452 | I9: 31.949681 | J9: 38.21749 | K9: 27.127527 | L9: 18.905042 | M9: 23.39172 | N9: 13.556458 | O9: 24.663616 | P9: 35.28264 | Q9: 26.451461 | R9: 10.103217 | S9: 37.636165 | T9: 22.717879 | U9: 8.103497 | V9: 16.103851
B10: 7 | C10: 118.7783 | D10: 177.10848 | E10: 139.59746 | F10: 286.11451 | G10: 839.18785 | H10: 113.52442 | I10: 219.06099 | J10: 173.52138 | K10: 169.89498 | L10: 118.68617 | M10: 148.5273 | N10: 130.85265 | O10: 105.54203 | P10: 72.910057 | Q10: 140.56796 | R10: 145.04998 | S10: 134.33116 | T10: 166.72636 | U10: 134.3404 | V10: 241.0823
B11: 8 | C11: 52.61925 | D11: 16.14636 | E11: 26.310179 | F11: 97.359695 | G11: 374.02271 | H11: 28.261021 | I11: 23.150731 | J11: 31.520711 | K11: 76.949132 | L11: 22.886214 | M11: 28.733223 | N11: 17.84907 | O11: 42.757097 | P11: 12.776513 | Q11: 14.484706 | R11: 7.4221752 | S11: 14.408651 | T11: 60.968428 | U11: 6.0823417 | V11: 28.920885
B12: 9 | C12: 339.42386 | D12: 101.41025 | E12: 316.43375 | F12: 495.20198 | G12: 1674.6148 | H12: 213.87614 | I12: 307.16552 | J12: 511.6289 | K12: 275.18271 | L12: 349.53829 | M12: 261.71155 | N12: 178.35642 | O12: 178.5729 | P12: 177.08365 | Q12: 247.19361 | R12: 21.664617 | S12: 189.24456 | T12: 245.05426 | U12: 372.69848 | V12: 292.3479
B13: 10 | C13: 106.90674 | D13: 83.685322 | E13: 111.76221 | F13: 221.00748 | G13: 465.86955 | H13: 36.764353 | I13: 133.04162 | J13: 134.2232 | K13: 158.85828 | L13: 182.29964 | M13: 75.807438 | N13: 26.332204 | O13: 65.087997 | P13: 46.068764 | Q13: 52.751456 | R13: 65.674718 | S13: 59.662397 | T13: 101.12361 | U13: 50.413623 | V13: 144.60442
B14: 11 | C14: 448.25916 | D14: 275.29694 | E14: 460.86241 | F14: 963.50621 | G14: 2032.6497 | H14: 196.39489 | I14: 322.38297 | J14: 324.39487 | K14: 502.48913 | L14: 402.03651 | M14: 285.22191 | N14: 92.859457 | O14: 226.24213 | P14: 255.22542 | Q14: 237.57537 | R14: 355.14789 | S14: 169.0051 | T14: 326.99985 | U14: 165.32031 | V14: 368.69581
... B34: 31 | C34: 128.18631 | D34: 128.45737 | E34: 138.70026 | F34: 340.13205 | G34: 1097.0339 | H34: 121.704 | I34: 216.18937 | J34: 205.89404 | K34: 235.64082 | L34: 134.72522 | M34: 111.0738 | N34: 201.34743 | O34: 109.06934 | P34: 69.879234 | Q34: 144.01362 | R34: 22.852795 | S34: 117.62825 | T34: 159.17837 | U34: 108.8612 | V34: 277.02099

Sheet Result 1
A1: C1 | B1: C2 | C1: C3 | D1: C4 | E1: C5 | F1: C6 | G1: C7 | H1: C8 | I1: C9 | J1: C10 | K1: C11 | L1: C12 | M1: C13 | N1: C14 | O1: C15 | P1: C16 | Q1: C17 | R1: C18 | S1: C19 | T1: C20 | U1: C21 | V1: C22 | W1: C23 | X1: C24 | Y1: C25 | Z1: C26 | AA1: C27 | AB1: C28 | AC1: C29 | AD1: C30 | AE1: C31 | AF1: C32 | AG1: C33 | AH1: C34 | AI1: C35 | AJ1: C36 | AK1: C37 | AL1: C38 | AM1: C39 | AN1: C40 | AO1: C41 | AP1: C42 | AQ1: C43 | AR1: C44 | AS1: C45 | AT1: C46 | AU1: C47 | AV1: C48 | AW1: C49 | AX1: C50 | AY1: C51 | AZ1: C52 | BA1: C53 | BB1: C54 | BC1: C55 | BD1: C56 | BE1: C57 | BF1: C58 | BG1: C59 | BH1: C60 | BI1: C61 | BJ1: C62 | BK1: C63 | BL1: C64 | BM1: C65 | BN1: C66 | BO1: C67 | BP1: C68 | BQ1: C69 | BR1: C70 | BS1: C71 | BT1: C72 | BU1: C73 | BV1: C74 | BW1: C75 | BX1: C76 | BY1: C77 | BZ1: C78 | CA1: C79 | CB1: C80 | CC1: C81 | CD1: C82 | CE1: C83 | CF1: C84 | CG1: C85 | CH1: C86 | CI1: C87 | CJ1: C88 | CK1: C89 | CL1: C90 | CM1: C91 | CN1: C92 | CO1: C93 | CP1: C94 | CQ1: C95 | CR1: C96 | CS1: C97 | CT1: C98 | CU1: C99 | CV1: C100 | CW1: C101 | CX1: C102 | CY1: C103 | CZ1: C104 | DA1: C105 | DB1: C106 | DC1: C107 | DD1: C108 | DE1: C109 | DF1: C110 | DG1: C111 | DH1: C112 | DI1: C113 | DJ1: C114 | DK1: C115 | DL1: C116 | DM1: C117 | DN1: C118 | DO1: C119 | DP1: C120 | DQ1: C121 | DR1: C122 | DS1: C123 | DT1: C124 | DU1: C125 | DV1: C126 | DW1: C127 | DX1: C128 | DY1: C129 | DZ1: C130 | EA1: C131 | EB1: C132 | EC1: C133 | ED1: C134 | EE1: C135 | EF1: C136 | EG1: C137 | EH1: C138 | EI1: C139 | EJ1: C140 | EK1: C141 | EL1: C142 | EM1: C143 | EN1: C144 | EO1: C145 | EP1: C146 | EQ1: C147 | ER1: C148 | ES1: C149 | ET1: C150 | EU1: C151 | EV1: C152 | EW1: C153 | EX1: C154 | EY1: C155 | EZ1: C156 | FA1: C157 | FB1: C158 | FC1: C159 | FD1: C160 | FE1: C161 | FF1: C162 | FG1: C163 | FH1: C164 | FI1: C165 | FJ1: C166 | FK1: C167 | FL1: C168 | FM1: C169 | FN1: C170 | FO1: C171 | FP1: C172 | FQ1: C173 | FR1: C174 | FS1: C175 | FT1: C176 | FU1: C177 | FV1: C178 | FW1: C179 | FX1: C180 | FY1: C181 | FZ1: C182 | GA1: C183 | GB1: C184 | GC1: C185 | GD1: C186 | GE1: C187 | GF1: C188 | GG1: C189 | GH1: C190 | GI1: C191 | GJ1: C192 | GK1: C193 | GL1: C194 | GM1: C195 | GN1: C196 | GO1: C197 | GP1: C198 | GQ1: C199 | GR1: C200 | GS1: C201 | GT1: C202 | GU1: C203 | GV1: C204 | GW1: C205 | GX1: C206 | GY1: C207 | GZ1: C208 | HA1: C209 | HB1: C210 | HC1: C211 | HD1: C212 | HE1: C213 | HF1: C214 | HG1: C215 | HH1: C216 | HI1: C217 | HJ1: C218 | HK1: C219 | HL1: C220 | HM1: C221 | HN1: C222 | HO1: C223 | HP1: C224 | HQ1: C225 | HR1: C226 | HS1: C227 | HT1: C228 | HU1: C229 | HV1: C230 | HW1: C231 | HX1: C232 | HY1: C233 | HZ1: C234 | IA1: C235 | IB1: C236 | IC1: C237 | ID1: C238 | IE1: C239 | IF1: C240 | IG1: C241 | IH1: C242 | II1: C243 | IJ1: C244 | IK1: C245 | IL1: C246 | IM1: C247 | IN1: C248 | IO1: C249 | IP1: C250 | IQ1: C251 | IR1: C252 | IS1: C253 | IT1: C254
A2: document | B2: 0 | C2: 1 | D2: 2 | E2: 3 | F2: 4 | G2: 5 | H2: 6 | I2: 7 | J2: 8 | K2: 9 | L2: 10 | M2: 11 | N2: 12 | O2: 13 | P2: 14 | Q2: 15 | R2: 16 | S2: 17 | T2: 18 | U2: 19 | V2: 20 | W2: 21 | X2: 22 | Y2: 23 | Z2: 24 | AA2: 25 | AB2: 26 | AC2: 27 | AD2: 28 | AE2: 29 | AF2: 30 | AG2: 31 | AH2: 32 | AI2: 33 | AJ2: 34 | AK2: 35 | AL2: 36 | AM2: 37 | AN2: 38 | AO2: 39 | AP2: 40 | AQ2: 41 | AR2: 42 | AS2: 43 | AT2: 44 | AU2: 45 | AV2: 46 | AW2: 47 | AX2: 48 | AY2: 49 | AZ2: 50 | BA2: 51 | BB2: 52 | BC2: 53 | BD2: 54 | BE2: 55 | BF2: 56 | BG2: 57 | BH2: 58 | BI2: 59 | BJ2: 60 | BK2: 61 | BL2: 62 | BM2: 63 | BN2: 64 | BO2: 65 | BP2: 66 | BQ2: 67 | BR2: 68 | BS2: 69 | BT2: 70 | BU2: 71 | BV2: 72 | BW2: 73 | BX2: 74 | BY2: 75 | BZ2: 76 | CA2: 77 | CB2: 78 | CC2: 79 | CD2: 80 | CE2: 81 | CF2: 82 | CG2: 83 | CH2: 84 | CI2: 85 | CJ2: 86 | CK2: 87 | CL2: 88 | CM2: 89 | CN2: 90 | CO2: 91 | CP2: 92 | CQ2: 93 | CR2: 94 | CS2: 95 | CT2: 96 | CU2: 97 | CV2: 98 | CW2: 99 | CX2: 100 | CY2: 101 | CZ2: 102 | DA2: 103 | DB2: 104 | DC2: 105 | DD2: 106 | DE2: 107 | DF2: 108 | DG2: 109 | DH2: 110 | DI2: 111 | DJ2: 112 | DK2: 113 | DL2: 114 | DM2: 115 | DN2: 116 | DO2: 117 | DP2: 118 | DQ2: 119 | DR2: 120 | DS2: 121 | DT2: 122 | DU2: 123 | DV2: 124 | DW2: 125 | DX2: 126 | DY2: 127 | DZ2: 128 | EA2: 129 | EB2: 130 | EC2: 131 | ED2: 132 | EE2: 133 | EF2: 134 | EG2: 135 | EH2: 136 | EI2: 137 | EJ2: 138 | EK2: 139 | EL2: 140 | EM2: 141 | EN2: 142 | EO2: 143 | EP2: 144 | EQ2: 145 | ER2: 146 | ES2: 147 | ET2: 148 | EU2: 149 | EV2: 150 | EW2: 151 | EX2: 152 | EY2: 153 | EZ2: 154 | FA2: 155 | FB2: 156 | FC2: 157 | FD2: 158 | FE2: 159 | FF2: 160 | FG2: 161 | FH2: 162 | FI2: 163 | FJ2: 164 | FK2: 166 | FL2: 167 | FM2: 168 | FN2: 169 | FO2: 170 | FP2: 171 | FQ2: 172 | FR2: 173 | FS2: 175 | FT2: 176 | FU2: 177 | FV2: 178 | FW2: 179 | FX2: 180 | FY2: 181 | FZ2: 182 | GA2: 183 | GB2: 184 | GC2: 185 | GD2: 186 | GE2: 188 | GF2: 190 | GG2: 191 | GH2: 194 | GI2: 195 | GJ2: 196 | GK2: 197 | GL2: 198 | GM2: 199 | GN2: 200 | GO2: 201 | GP2: 202 | GQ2: 203 | GR2: 204 | GS2: 205 | GT2: 206 | GU2: 207 | GV2: 208 | GW2: 209 | GX2: 210 | GY2: 211 | GZ2: 212 | HA2: 213 | HB2: 214 | HC2: 215 | HD2: 216 | HE2: 217 | HF2: 219 | HG2: 220 | HH2: 221 | HI2: 223 | HJ2: 224 | HK2: 228 | HL2: 229 | HM2: 230 | HN2: 231 | HO2: 232 | HP2: 233 | HQ2: 234 | HR2: 236 | HS2: 237 | HT2: 241 | HU2: 242 | HV2: 243 | HW2: 245 | HX2: 252 | HY2: 253 | HZ2: 254 | IA2: 256 | IB2: 259 | IC2: 260 | ID2: 261 | IE2: 264 | IF2: 265 | IG2: 270 | IH2: 271 | II2: 272 | IJ2: 273 | IK2: 278 | IL2: 285 | IM2: 288 | IN2: 289 | IO2: 292 | IP2: 296 | IQ2: 298 | IR2: 302 | IS2: 312 | IT2: 355
A3: 0 | B3: 51.851002 | C3: 1.0245254 | D3: 2.9674291 | E3: 32.557525 | F3: 23.14007 | G3: 7.6531817 | H3: 16.256712 | I3: 26.384739 | J3: 5.0016793 | K3: 19.35283 | L3: 97.208034 | M3: 3.60319 | N3: 5.4719758 | O3: 40.643527 | P3: 375.03324 | Q3: 3.5212756 | R3: 13.805614 | S3: 14.578996 | T3: 6.4355444 | U3: 4.2528102 | V3: 28.261021 | W3: 4.7929326 | X3: 14.875216 | Y3: 23.329239 | Z3: 9.4370294 | AA3: 30.386693 | AB3: 4.1244312 | AC3: 5.1147713 | AD3: 9.4238381 | AE3: 2.3903747 | AF3: 6.2885761 | AG3: 7.9306341 | AH3: 75.952829 | AI3: 7.4875501 | AJ3: 6.8517249 | AK3: 22.886214 | AL3: 10.752763 | AM3: 5.2975865 | AN3: 3.0666308 | AO3: 8.9970973 | AP3: 28.733223 | AQ3: 7.5162994 | AR3: 1.7701907 | AS3: 14.003673 | AT3: 1.2430281 | AU3: 13.173992 | AV3: 18.007168 | AW3: 1.3299031 | AX3: 10.486291 | AY3: 5.5434359 | AZ3: 23.274879 | BA3: 5.1682765 | BB3: 20.961038 | BC3: 2.7325395 | BD3: 6.4499663 | BE3: 3.0290509 | BF3: 3.2617411 | BG3: 1.6991894 | BH3: 13.118785 | BI3: 3.1326686 | BJ3: 4.3869719 | BK3: 0.99880964 | BL3: 0.37896345 | BM3: 25.628221 | BN3: 17.2936 | BO3: 5.9952671 | BP3: 4.1097145 | BQ3: 4.1745933 | BR3: 5.3627642 | BS3: 0.45947873 | BT3: 8.4777366 | BU3: 4.6013443 | BV3: 17.242799 | BW3: 8.2202565 | BX3: 42.757097 | BY3: 12.80601 | BZ3: 15.318453 | CA3: 5.6238489 | CB3: 0.046962256 | CC3: 8.9298334 | CD3: 12.190771 | CE3: 0.38823182 | CF3: 4.0472588 | CG3: 0.089993182 | CH3: 2.5657062 | CI3: 8.0607234 | CJ3: 0.10650728 | CK3: 1.7259663 | CL3: 1.0039748 | CM3: 4.0515821 | CN3: 28.915584 | CO3: 2.8885751 | CP3: 2.294282 | CQ3: 6.1897009 | CR3: 34.206579 | CS3: 7.4221752 | CT3: 14.408651 | CU3: 60.968428 | CV3: 1.1584712 | CW3: 2.0146932 | CX3: 0.0030591216 | CY3: 4.2481354e-18 | CZ3: 0 | DA3: 0.19207182 | DB3: 0.14513378 | DC3: 2.9866169 | DD3: 1.0868684 | DE3: 4.9777101 | DF3: 0 | DG3: 14.885791 | DH3: 7.9953109 | DI3: 1.9369466 | DJ3: 6.0823417 | DK3: 1.6837601 | DL3: 0.2002544 | DM3: 0.088982134 | DN3: 6.6129359 | DO3: 5.9136797 | DP3: 1.0420458 | DQ3: 6.8355271 | DR3: 1.3642059 | DS3: 5.0961004 | DT3: 14.300969 | DU3: 0.0037750482 | DV3: 2.972168 | DW3: 6.4951478 | DX3: 7.8523676 | DY3: 16.2411 | DZ3: 1.9418666 | EA3: 4.3920252 | EB3: 8.0379521 | EC3: 0.79346318 | ED3: 0 | EE3: 1.282885 | EF3: 3.3451368 | EG3: 5.4053893 | EH3: 5.5823359 | EI3: 3.5781367 | EJ3: 0 | EK3: 3.8838076 | EL3: 3.9598936 | EM3: 17.496252 | EN3: 0.11451844 | EO3: 12.762923 | EP3: 0.1474215 | EQ3: 3.0153989 | ER3: 0.13918118 | ES3: 0.18387617 | ET3: 2.5664171 | EU3: 2.9594481 | EV3: 1.1595967 | EW3: 3.9049364 | EX3: 14.038329 | EY3: 5.9822532 | EZ3: 1.2810793 | FA3: 0.28984238 | FB3: 10.012614 | FC3: 0.76736491 | FD3: 0 | FE3: 0.18758808 | FF3: 0 | FG3: 0 | FH3: 0.43207953 | FI3: 0 | FJ3: 1.6877183 | FK3: 0.96474723 | FL3: 4.9968425 | FM3: 9.2350745 | FN3: 3.9999823 | FO3: 0 | FP3: 0 | FQ3: 0.32353594 | FR3: 2.2304579 | FS3: 2.3024525 | FT3: 3.0365864 | FU3: 0 | FV3: 0 | FW3: 14.954982 | FX3: 0 | FY3: 0 | FZ3: 0 | GA3: 0.33061932 | GB3: 0 | GC3: 0.7659121 | GD3: 0 | GE3: 0 | GF3: 0 | GG3: 10.183926 | GH3: 0 | GI3: 1.6528582 | GJ3: 0 | GK3: 0 | GL3: 0.020955985 | GM3: 1.9477348 | GN3: 11.921747 | GO3: 0 | GP3: 0.40903956 | GQ3: 0 | GR3: 0 | GS3: 0 | GT3: 0.32737933 | GU3: 1.9989222 | GV3: 1.9741135 | GW3: 0.24582733 | GX3: 0 | GY3: 0.0094534433 | GZ3: 0 | HA3: 0 | HB3: 0 | HC3: 0 | HD3: 0 | HE3: 0 | HF3: 0 | HG3: 28.920885 | HH3: 0 | HI3: 0.91780434 | HJ3: 0 | HK3: -5.9893424e-17 | HL3: 0.043866831 | HM3: 0.23053474 | HN3: 0 | HO3: 1.0127734 | HP3: 1.0060968 | HQ3: 1.998938 | HR3: 1.0712198 | HS3: 3.2424812 | HT3: 1.46014 | HU3: 0.98205308 | HV3: -4.4408921e-16 | HW3: 0 | HX3: 0 | HY3: 1.4065726 | HZ3: 7.7065902e-18 | IA3: 5.0103249 | IB3: 0 | IC3: 1.06465 | ID3: 0 | IE3: 0 | IF3: 0 | IG3: 0.15659522 | IH3: 1.9944195 | II3: 0 | IJ3: 0 | IK3: 0.0061610511 | IL3: 0 | IM3: 0 | IN3: 1.1016278 | IO3: 0 | IP3: 0.00058813294 | IQ3: 4.9453218 | IR3: 3.1438705 | IS3: 0 | IT3: 0
A4: 1 | B4: 306.08778 | C4: 12.536708 | D4: 64.411952 | E4: 45.645451 | F4: 194.32531 | G4: 44.685241 | H4: 82.448464 | I4: 274.51616 | J4: 33.562384 | K4: 79.543681 | L4: 415.05036 | M4: 139.01368 | N4: 73.073565 | O4: 106.62721 | P4: 1255.2543 | Q4: 81.235447 | R4: 59.709173 | S4: 47.561558 | T4: 25.442954 | U4: 100.13233 | V4: 166.87932 | W4: 14.156036 | X4: 71.519073 | Y4: 257.69948 | Z4: 125.01182 | AA4: 433.84638 | AB4: 23.29541 | AC4: 67.443731 | AD4: 94.656986 | AE4: 75.418519 | AF4: 78.435934 | AG4: 97.894829 | AH4: 246.61223 | AI4: 43.443157 | AJ4: 23.174298 | AK4: 306.86222 | AL4: 120.18108 | AM4: 69.800999 | AN4: 15.582587 | AO4: 8.6765848 | AP4: 239.22045 | AQ4: 43.813552 | AR4: 104.1308 | AS4: 61.504311 | AT4: 24.122165 | AU4: 52.611342 | AV4: 116.35481 | AW4: 14.340373 | AX4: 73.787911 | AY4: 40.074507 | AZ4: 161.473 | BA4: 25.404738 | BB4: 156.66459 | BC4: 16.637333 | BD4: 289.27853 | BE4: 45.159701 | BF4: 71.845799 | BG4: 91.879913 | BH4: 57.562639 | BI4: 44.16833 | BJ4: 32.917228 | BK4: 47.989836 | BL4: 12.670188 | BM4: 189.31326 | BN4: 58.302486 | BO4: 37.806173 | BP4: 142.61713 | BQ4: 48.056174 | BR4: 106.13668 | BS4: 3.08267 | BT4: 58.299275 | BU4: 20.625008 | BV4: 132.38438 | BW4: 81.636862 | BX4: 171.19988 | BY4: 169.65558 | BZ4: 233.98395 | CA4: 58.948818 | CB4: 6.2854867 | CC4: 50.921331 | CD4: 140.43724 | CE4: 7.6179044 | CF4: 2.3673961 | CG4: 24.974118 | CH4: 13.461757 | CI4: 30.978766 | CJ4: 18.603661 | CK4: 17.274147 | CL4: 52.440511 | CM4: 82.87755 | CN4: 96.80141 | CO4: 0.50443262 | CP4: 22.576862 | CQ4: 47.195298 | CR4: 149.61832 | CS4: 18.442321 | CT4: 122.63486 | CU4: 203.92765 | CV4: 1.9632311 | CW4: 13.373604 | CX4: 21.894746 | CY4: 0.054037507 | CZ4: 9.9056355e-05 | DA4: 11.578853 | DB4: 7.0837146 | DC4: 51.268107 | DD4: 118.27748 | DE4: 9.0581938 | DF4: 12.126357 | DG4: 6.3200323 | DH4: 45.915885 | DI4: 16.905561 | DJ4: 331.30013 | DK4: 1.7553287 | DL4: 1.3010059 | DM4: 0.91616491 | DN4: 15.296576 | DO4: 10.240636 | DP4: 3.2191115 | DQ4: 40.080484 | DR4: 31.30458 | DS4: 8.275804 | DT4: 52.351735 | DU4: 28.327851 | DV4: 121.32421 | DW4: 53.656433 | DX4: 22.592249 | DY4: 45.479334 | DZ4: 0 | EA4: 5.0947354 | EB4: 80.877228 | EC4: 14.362505 | ED4: 9.4582078 | EE4: 14.536049 | EF4: 72.903765 | EG4: 18.903362 | EH4: 9.0307156 | EI4: 36.265699 | EJ4: 18.963082 | EK4: 42.996019 | EL4: 3.2053061 | EM4: 139.29311 | EN4: 9.6722966 | EO4: 124.1527 | EP4: 0.89324399 | EQ4: 94.007955 | ER4: 0.3280002 | ES4: 2.2621595 | ET4: 67.922685 | EU4: 7.3411254 | EV4: 35.250713 | EW4: 4.8808061 | EX4: 107.21878 | EY4: 25.163482 | EZ4: 2.5429291 | FA4: 13.837959 | FB4: 72.956738 | FC4: 4.3285061 | FD4: 10.837945 | FE4: 3.6222387 | FF4: 3.2597622e-16 | FG4: 1.2684505 | FH4: 0.64767995 | FI4: 0.022190712 | FJ4: 58.128122 | FK4: 34.82917 | FL4: 33.978529 | FM4: 31.932258 | FN4: 26.840433 | FO4: 3.001846 | FP4: 15.696143 | FQ4: 6.7874092 | FR4: 21.272229 | FS4: 17.089277 | FT4: 18.4194 | FU4: 1.355924e-18 | FV4: 27.981272 | FW4: 39.217536 | FX4: 0 | FY4: 2.1189039 | FZ4: 17.249877 | GA4: 1.9867213 | GB4: 18.661346 | GC4: 2.7863056 | GD4: 2.180957 | GE4: 0.0064477096 | GF4: 1.6586022 | GG4: 82.566817 | GH4: 5.3402704 | GI4: 20.196913 | GJ4: -0.36566929 | GK4: 4.4809675 | GL4: 11.165507 | GM4: 3.9013249 | GN4: 35.922238 | GO4: 0.54499113 | GP4: 0.015583779 | GQ4: 0 | GR4: 1.1388661 | GS4: 8.265003 | GT4: 25.310476 | GU4: 26.008021 | GV4: 10.577009 | GW4: 43.320058 | GX4: 0.60745802 | GY4: 1.1004807 | GZ4: 1.6022845 | HA4: 93.020276 | HB4: 15.207153 | HC4: 0 | HD4: 0.03818583 | HE4: 14.906224 | HF4: 4.4637969 | HG4: 254.23359 | HH4: 25.092905 | HI4: 20.824829 | HJ4: 0.92567392 | HK4: 0.0046423092 | HL4: 0.13160049 | HM4: 4.5035325 | HN4: 0 | HO4: 62.02728 | HP4: 13.946933 | HQ4: 40.978229 | HR4: 1.3048192 | HS4: 16.144674 | HT4: 33.276452 | HU4: 0 | HV4: 1.1457691 | HW4: 13.591058 | HX4: 1.3299148e-14 | HY4: 19.732144 | HZ4: 5.6970101 | IA4: 123.10624 | IB4: 1.6272883 | IC4: 7.811138 | ID4: 1.9620922 | IE4: 0.13189867 | IF4: 0 | IG4: 4.0309267 | IH4: 24.930243 | II4: 0 | IJ4: 4.9456892 | IK4: 1.6618328 | IL4: 8.1816822 | IM4: 1.7018915e-14 | IN4: 6.6260227 | IO4: 7.001498 | IP4: 15.270611 | IQ4: 34.887244 | IR4: 0 | IS4: -4.0056295e-16 | IT4: 0
A5: 2 | B5: 89.593904 | C5: 4.3301592 | D5: 6.6933575 | E5: 15.857177 | F5: 21.70031 | G5: 21.716857 | H5: 80.369672 | I5: 88.613177 | J5: 9.1131879 | K5: 11.986869 | L5: 158.68255 | M5: 15.314446 | N5: 17.003816 | O5: 41.241365 | P5: 376.95829 | Q5: 33.798659 | R5: 30.494112 | S5: 8.5461576 | T5: 5.9051741 | U5: 11.437828 | V5: 28.346466 | W5: 10.164059 | X5: 12.292489 | Y5: 106.97509 | Z5: 12.509822 | AA5: 65.232164 | AB5: 7.7992245 | AC5: 11.976121 | AD5: 16.671506 | AE5: 18.404884 | AF5: 31.568659 | AG5: 31.28931 | AH5: 81.955509 | AI5: 19.837303 | AJ5: 9.6704916 | AK5: 155.31725 | AL5: 27.006365 | AM5: 10.398463 | AN5: 1.0742874 | AO5: 8.305645 | AP5: 56.668944 | AQ5: 4.4898003 | AR5: 3.0928679 | AS5: 31.084826 | AT5: 5.2943582 | AU5: 14.217683 | AV5: 30.985712 | AW5: 2.1367162 | AX5: 48.262609 | AY5: 12.304107 | AZ5: 43.777096 | BA5: 1.0675621 | BB5: 14.276855 | BC5: 6.6068272 | BD5: 0.39396091 | BE5: 55.671136 | BF5: 17.302068 | BG5: 7.4458809 | BH5: 82.190477 | BI5: 16.051621 | BJ5: 5.7797967 | BK5: 4.0422121 | BL5: 6.7999509 | BM5: 39.867533 | BN5: 20.767779 | BO5: 4.5306686 | BP5: 51.323458 | BQ5: 10.642221 | BR5: 26.091227 | BS5: 0.40347109 | BT5: 9.7630254 | BU5: 5.4369257 | BV5: 19.647866 | BW5: 3.2957567 | BX5: 45.323145 | BY5: 32.056812 | BZ5: 49.996293 | CA5: 31.27333 | CB5: 0.56411327 | CC5: 25.999991 | CD5: 45.534606 | CE5: 2.2221845 | CF5: 1.9118145 | CG5: 2.0162086 | CH5: 3.3490741 | CI5: 1.9977542 | CJ5: 5.473572 | CK5: 9.0328358 | CL5: 58.953854 | CM5: 10.254629 | CN5: 16.309143 | CO5: 3.9664198 | CP5: 3.5361011 | CQ5: 16.419182 | CR5: 24.72866 | CS5: 65.084435 | CT5: 42.538984 | CU5: 81.452215 | CV5: 1.2347237 | CW5: 2.7413868 | CX5: 4.9943135 | CY5: 0.05250587 | CZ5: 96.100668 | DA5: 3.1215872 | DB5: 0.20228336 | DC5: 9.6496852 | DD5: 3.0377963 | DE5: 12.12739 | DF5: 1.5272933 | DG5: 2.4566673 | DH5: 8.5019009 | DI5: 1.2262597 | DJ5: 65.454006 | DK5: 0.0027952455 | DL5: 1.5906569 | DM5: 4.3017652 | DN5: 17.523913 | DO5: 0.98561329 | DP5: 2.3169413 | DQ5: 26.096674 | DR5: 2.9556574 | DS5: 16.071138 | DT5: 8.3556983 | DU5: 2.8721975 | DV5: 27.522202 | DW5: 22.950957 | DX5: 1.0109766 | DY5: 24.589489 | DZ5: 0 | EA5: 1.9368592 | EB5: 19.465659 | EC5: 3.3716642 | ED5: 0.5150195 | EE5: 8.5028398 | EF5: 15.530282 | EG5: 14.275834 | EH5: 3.9953502 | EI5: 12.829307 | EJ5: 1.0618115 | EK5: 17.038799 | EL5: 1.5459494 | EM5: 22.208609 | EN5: 9.5324852 | EO5: 18.578101 | EP5: 0 | EQ5: 8.9980762 | ER5: 0.00023391439 | ES5: 4.3317723 | ET5: 7.8242686 | EU5: 1.323525 | EV5: 0.087249599 | EW5: 4.9618564 | EX5: 25.88995 | EY5: 19.068853 | EZ5: 0.15980255 | FA5: 1.0899353 | FB5: 11.4522 | FC5: 1.2082163 | FD5: 0 | FE5: 0.2561344 | FF5: 0 | FG5: 0.91013721 | FH5: 2.9814631 | FI5: 0 | FJ5: 3.2952353 | FK5: 3.1476534 | FL5: 4.9968425 | FM5: 15.121876 | FN5: 4.108313 | FO5: 0.11411886 | FP5: 0.97960774 | FQ5: 1.0534721 | FR5: 13.808855 | FS5: 12.15822 | FT5: 3.8374387 | FU5: 54.999965 | FV5: 5.7140909 | FW5: 3.8935549 | FX5: 0 | FY5: 2.8931002 | FZ5: 2.0310633 | GA5: 1.947502 | GB5: 0.72523498 | GC5: 0.40393377 | GD5: 0.96106307 | GE5: 1.1980917 | GF5: 1.1830047 | GG5: 19.223432 | GH5: 0.82070494 | GI5: 5.5496834 | GJ5: 0 | GK5: 0 | GL5: 3.6359983 | GM5: 0.97386739 | GN5: 6.9279432 | GO5: 0 | GP5: 0.1976454 | GQ5: 0.23934753 | GR5: 2.1252535 | GS5: 0.9726222 | GT5: 11.075162 | GU5: 7.0134284 | GV5: 3.9981849 | GW5: 3.3795039 | GX5: 0.013288341 | GY5: 0.27500436 | GZ5: 0 | HA5: 13.997581 | HB5: 7.7499123 | HC5: 0 | HD5: 0 | HE5: 0.65354713 | HF5: 1.884476 | HG5: 159.5635 | HH5: 0 | HI5: 3.3041703 | HJ5: 0 | HK5: 0.69503631 | HL5: 0.01704837 | HM5: 3.6929913 | HN5: 2.220446e-16 | HO5: 8.996879 | HP5: 3.984838 | HQ5: 0.0015800573 | HR5: 1.7919007 | HS5: 2.0880366 | HT5: 7.7217542 | HU5: 0 | HV5: 0 | HW5: 4.0219116 | HX5: 0 | HY5: 2.9889238 | HZ5: 11.218994 | IA5: 2.0128617 | IB5: 0 | IC5: 2.5943752 | ID5: 6.8673229 | IE5: 2.1195401 | IF5: 0 | IG5: 0 | IH5: 0.00052625195 | II5: 0 | IJ5: 0.013067036 | IK5: 4.2802836 | IL5: 1.9796021 | IM5: 9.6772665e-15 | IN5: 1.7866198 | IO5: 2.9999947 | IP5: 0.001589842 | IQ5: 9.7428503 | IR5: 0 | IS5: 0 | IT5: 0
A6: 3 | B6: 430.80043 | C6: 19.704673 | D6: 71.815228 | E6: 78.612383 | F6: 139.26189 | G6: 69.126713 | H6: 289.38459 | I6: 458.13041 | J6: 64.78954 | K6: 116.65401 | L6: 893.64199 | M6: 139.97881 | N6: 100.22681 | O6: 106.94032 | P6: 1775.6668 | Q6: 70.984072 | R6: 207.15586 | S6: 113.27098 | T6: 103.98005 | U6: 89.01212 | V6: 185.60125 | W6: 28.58489 | X6: 69.563431 | Y6: 300.2922 | Z6: 89.242663 | AA6: 327.92901 | AB6: 45.951434 | AC6: 103.58056 | AD6: 109.56508 | AE6: 165.22102 | AF6: 90.357352 | AG6: 95.945805 | AH6: 447.34327 | AI6: 75.06595 | AJ6: 52.524243 | AK6: 373.00803 | AL6: 114.40666 | AM6: 51.053239 | AN6: 20.017483 | AO6: 61.515867 | AP6: 263.04018 | AQ6: 31.16032 | AR6: 61.716278 | AS6: 165.35749 | AT6: 29.707503 | AU6: 101.79976 | AV6: 174.21931 | AW6: 17.828081 | AX6: 146.9956 | AY6: 87.644534 | AZ6: 178.4392 | BA6: 46.237872 | BB6: 49.995082 | BC6: 38.47881 | BD6: 65.040435 | BE6: 80.684978 | BF6: 91.824159 | BG6: 29.514242 | BH6: 124.0007 | BI6: 40.569384 | BJ6: 33.051606 | BK6: 128.25638 | BL6: 20.815691 | BM6: 268.22482 | BN6: 132.7975 | BO6: 47.224262 | BP6: 100.34609 | BQ6: 27.665811 | BR6: 110.9424 | BS6: 4.6596728 | BT6: 92.386234 | BU6: 53.053058 | BV6: 91.354876 | BW6: 59.619278 | BX6: 216.61521 | BY6: 248.512 | BZ6: 228.44635 | CA6: 140.17009 | CB6: 11.714288 | CC6: 108.24326 | CD6: 168.71161 | CE6: 32.332709 | CF6: 35.284258 | CG6: 46.540273 | CH6: 49.281758 | CI6: 32.590348 | CJ6: 20.299037 | CK6: 21.802761 | CL6: 28.017403 | CM6: 47.421168 | CN6: 60.54052 | CO6: 5.84258 | CP6: 20.20459 | CQ6: 68.270499 | CR6: 116.99101 | CS6: 304.19681 | CT6: 151.64575 | CU6: 285.88389 | CV6: 23.336955 | CW6: 17.790501 | CX6: 33.430847 | CY6: 28.042519 | CZ6: 0.081311162 | DA6: 3.7985685 | DB6: 2.6441648 | DC6: 98.892508 | DD6: 20.075808 | DE6: 33.20482 | DF6: 17.172169 | DG6: 103.11406 | DH6: 61.027255 | DI6: 27.988044 | DJ6: 158.61524 | DK6: 0.12831905 | DL6: 30.725018 | DM6: 1.016751 | DN6: 22.671944 | DO6: 5.5457784 | DP6: 9.3911379 | DQ6: 79.531858 | DR6: 23.439199 | DS6: 65.250749 | DT6: 100.15469 | DU6: 25.689424 | DV6: 62.186248 | DW6: 69.345055 | DX6: 4.9077297 | DY6: 80.31869 | DZ6: 2.133585 | EA6: 31.163734 | EB6: 158.20295 | EC6: 21.951396 | ED6: 24.722772 | EE6: 14.537465 | EF6: 20.419944 | EG6: 69.057804 | EH6: 10.838095 | EI6: 44.086677 | EJ6: 21.507292 | EK6: 23.161624 | EL6: 25.832518 | EM6: 198.86788 | EN6: 16.314716 | EO6: 65.699549 | EP6: 48.742814 | EQ6: 93.988396 | ER6: 15.813205 | ES6: 14.669785 | ET6: 25.880042 | EU6: 17.455628 | EV6: 1.3538302 | EW6: 14.974239 | EX6: 102.85031 | EY6: 49.977333 | EZ6: 5.0621935 | FA6: 10.330343 | FB6: 157.08871 | FC6: 1.2862966 | FD6: 2.6528972 | FE6: 0.038094862 | FF6: 11 | FG6: 4.2535134 | FH6: 4.3360746 | FI6: 68.005795 | FJ6: 65.566181 | FK6: 50.42701 | FL6: 14.998192 | FM6: 86.670813 | FN6: 43.965068 | FO6: 5.9964459 | FP6: 10.314014 | FQ6: 7.7782278 | FR6: 36.175995 | FS6: 27.860321 | FT6: 2.0140661 | FU6: 2.8737244e-18 | FV6: 12.778249 | FW6: 77.697642 | FX6: 0 | FY6: 5.2805761 | FZ6: 7.0928741 | GA6: 9.5277139 | GB6: 19.475547 | GC6: 14.07593 | GD6: 0.96106307 | GE6: 0.029004329 | GF6: 3.2374913 | GG6: 156.58221 | GH6: 13.521382 | GI6: 19.146592 | GJ6: 0 | GK6: 2.1722331 | GL6: 9.4521158 | GM6: 45.797595 | GN6: 32.521881 | GO6: 1.4844181 | GP6: 2.8325599 | GQ6: 6.0730683 | GR6: 0.12378661 | GS6: 4.3344238 | GT6: 25.965235 | GU6: 26.985449 | GV6: 19.234379 | GW6: 24.505566 | GX6: 5.1423885 | GY6: 0.29885472 | GZ6: 1.5947763 | HA6: 22.032542 | HB6: 8.0355849 | HC6: 3.3190479e-15 | HD6: 1.5401376 | HE6: 0.016713105 | HF6: 27.96426 | HG6: 321.45353 | HH6: 76.365181 | HI6: 28.609038 | HJ6: 0.92567392 | HK6: 1.2790719 | HL6: 58.039509 | HM6: 3.5318088 | HN6: 6 | HO6: 56.042942 | HP6: 38.059599 | HQ6: 5.1377692 | HR6: 1.0712198 | HS6: 25.098123 | HT6: 43.411362 | HU6: 4.9434108 | HV6: 1.7503086 | HW6: 3.9888313 | HX6: -1.4985375e-19 | HY6: 39.451181 | HZ6: 9.1482548 | IA6: 53.143208 | IB6: 0.35344759 | IC6: 10.914285 | ID6: 0 | IE6: 4.9874919 | IF6: 0 | IG6: 19.082596 | IH6: 13.014123 | II6: 0 | IJ6: 6.1866596 | IK6: 5.0352162 | IL6: 8.1310379 | IM6: 0 | IN6: 3.4067591 | IO6: 9.007335 | IP6: 0.31957048 | IQ6: 12.180755 | IR6: 0 | IS6: 2.9504469e-18 | IT6: 0
A7: 4 | B7: 173.07534 | C7: 79.44766 | D7: 3.0295685e+16 | E7: 91.775669 | F7: 62.51591 | G7: 48.467624 | H7: 104.89638 | I7: 218.6769 | J7: 37.952279 | K7: 47.910905 | L7: 312.66391 | M7: 67.637136 | N7: 26.392085 | O7: 123.84673 | P7: 1516.8056 | Q7: 65.718609 | R7: 105.02276 | S7: 71.011958 | T7: 102.51647 | U7: 55.483815 | V7: 145.67565 | W7: 30.769255 | X7: 58.547137 | Y7: 346.13357 | Z7: 115.18704 | AA7: 572.00817 | AB7: 28.776117 | AC7: 55.785099 | AD7: 97.669105 | AE7: 22.655841 | AF7: 41.163046 | AG7: 73.330264 | AH7: 467.65299 | AI7: 39.345269 | AJ7: 34.896899 | AK7: 230.21074 | AL7: 138.53551 | AM7: 24.010665 | AN7: 17.066349 | AO7: 63.771335 | AP7: 193.62484 | AQ7: 14.169066 | AR7: 24.555029 | AS7: 99.071483 | AT7: 32.19871 | AU7: 129.57582 | AV7: 171.93766 | AW7: 10.517842 | AX7: 99.217949 | AY7: 57.099334 | AZ7: 113.13149 | BA7: 45.008598 | BB7: 54.825584 | BC7: 23.258239 | BD7: 41.121594 | BE7: 53.555833 | BF7: 68.56786 | BG7: 8.478284 | BH7: 168.17439 | BI7: 35.953133 | BJ7: 22.124225 | BK7: 107.13902 | BL7: 7.1141108 | BM7: 40.62041 | BN7: 57.080001 | BO7: 67.224901 | BP7: 46.481249 | BQ7: 21.476697 | BR7: 80.165494 | BS7: 7.7968733 | BT7: 26.52419 | BU7: 37.008916 | BV7: 172.24455 | BW7: 115.28301 | BX7: 86.66805 | BY7: 88.673098 | BZ7: 111.47116 | CA7: 51.88321 | CB7: 6.8274468 | CC7: 54.041045 | CD7: 103.68267 | CE7: 46.089145 | CF7: 19.937134 | CG7: 1.948341 | CH7: 47.970871 | CI7: 24.265284 | CJ7: 30.415462 | CK7: 15.307221 | CL7: 3.8282158 | CM7: 51.399698 | CN7: 119.94495 | CO7: 42.823136 | CP7: 13.423461 | CQ7: 66.095958 | CR7: 84.669385 | CS7: 164.15151 | CT7: 158.4752 | CU7: 228.24771 | CV7: 1.2552855 | CW7: 24.750621 | CX7: 30.436046 | CY7: 5.0987441 | CZ7: 0.23478824 | DA7: 10.894086 | DB7: 4.3161268 | DC7: 33.693816 | DD7: 19.196289 | DE7: 23.978094 | DF7: 10.793875 | DG7: 9.0558377 | DH7: 36.239987 | DI7: 13.785887 | DJ7: 107.82253 | DK7: 2.6817857 | DL7: 0.67572913 | DM7: 3.7799303 | DN7: 66.673202 | DO7: 24.963704 | DP7: 28.521012 | DQ7: 60.057429 | DR7: 22.445223 | DS7: 31.66925 | DT7: 75.210745 | DU7: 32.588172 | DV7: 77.423444 | DW7: 41.511133 | DX7: 5.8892757 | DY7: 54.554754 | DZ7: 0.44645103 | EA7: 12.870891 | EB7: 111.7895 | EC7: 4.0003254 | ED7: 5.1262913 | EE7: 12.061981 | EF7: 107.46992 | EG7: 49.306861 | EH7: 12.503109 | EI7: 30.179322 | EJ7: 21.782534 | EK7: 50.489923 | EL7: 22.754566 | EM7: 124.84256 | EN7: 6.7342768 | EO7: 88.988694 | EP7: 4.2635058 | EQ7: 16.002293 | ER7: 0.48433595 | ES7: 10.467744 | ET7: 111.11725 | EU7: 8.3235999 | EV7: 4.2945117 | EW7: 15.022537 | EX7: 96.983996 | EY7: 28.182713 | EZ7: 14.490682 | FA7: 8.5097985 | FB7: 44.70853 | FC7: 9.6038064 | FD7: 7.5866457 | FE7: 1.8260824 | FF7: -3.6681286e-17 | FG7: 0.89202109 | FH7: 9.6535693 | FI7: 3.7509126e-18 | FJ7: 51.633048 | FK7: 20.018854 | FL7: 9.0035663 | FM7: 90.002736 | FN7: 47.200541 | FO7: 0.18854545 | FP7: 0.023017587 | FQ7: 10.229232 | FR7: 29.392525 | FS7: 14.234798 | FT7: 32.455646 | FU7: 1.8089216e-19 | FV7: 20.384212 | FW7: 35.094722 | FX7: 0 | FY7: 3.3656301 | FZ7: 5.1037944 | GA7: 3.3528188 | GB7: 33.29931 | GC7: 3.5689451 | GD7: 2.180957 | GE7: 3.0484824 | GF7: 2.5174827 | GG7: 33.080991 | GH7: 8.3754312 | GI7: 18.19807 | GJ7: 0 | GK7: 1.0747902 | GL7: 7.4681617 | GM7: 1.1332531 | GN7: 38.59854 | GO7: 1.3428256 | GP7: 0.1080219 | GQ7: 0.1468437 | GR7: 22.839387 | GS7: 5.8711501 | GT7: 12.067945 | GU7: 18.008037 | GV7: 11.905135 | GW7: 35.671107 | GX7: 5.1423885 | GY7: 55.301212 | GZ7: 0.9504248 | HA7: 14.022938 | HB7: 21.20021 | HC7: 0 | HD7: 5.1595135 | HE7: -1.0445896e-16 | HF7: 23.975387 | HG7: 106.67224 | HH7: 1.9938835 | HI7: 28.189848 | HJ7: 0.91035313 | HK7: 7.9941462 | HL7: 2.1089979 | HM7: 7.3613189 | HN7: 2.984406e-17 | HO7: 43.019258 | HP7: 9.0038086 | HQ7: 13.992566 | HR7: 4.7198188 | HS7: 4.6619251 | HT7: 40.554614 | HU7: 1.9641062 | HV7: 2.5056325 | HW7: 1.9833307 | HX7: 0.16646068 | HY7: 27.804264 | HZ7: 3.2054565 | IA7: 169.96909 | IB7: 5.1042237 | IC7: 12.869807 | ID7: 2.145263 | IE7: 0.0029225187 | IF7: 0 | IG7: 0.64408838 | IH7: 6.0262975 | II7: 0 | IJ7: 1.0853915 | IK7: 2.4927492 | IL7: 23.469507 | IM7: 1.2715399e-14 | IN7: 4.1750307 | IO7: 31.999943 | IP7: 0.025951342 | IQ7: 26.087153 | IR7: 0 | IS7: 5.6724131e-17 | IT7: 0
A8: 5 | B8: 36.46027 | C8: 0.51950732 | D8: 2.5401355 | E8: 30.48216 | F8: 26.890952 | G8: 6.0836636 | H8: 20.030444 | I8: 32.701488 | J8: 18.249632 | K8: 11.634562 | L8: 141.92388 | M8: 5.9701525 | N8: 11.362619 | O8: 51.46273 | P8: 573.86784 | Q8: 10.105686 | R8: 36.020834 | S8: 16.753427 | T8: 6.5568567 | U8: 6.3181973 | V8: 20.934039 | W8: 3.2218896 | X8: 26.035254 | Y8: 98.002564 | Z8: 21.417382 | AA8: 226.7084 | AB8: 4.6064898 | AC8: 14.321722 | AD8: 7.1008397 | AE8: 3.8001069 | AF8: 15.210981 | AG8: 10.049279 | AH8: 202.14597 | AI8: 15.216061 | AJ8: 7.6704803 | AK8: 71.353702 | AL8: 10.384351 | AM8: 5.3503984 | AN8: 0.22518574 | AO8: 1.6016302 | AP8: 45.739766 | AQ8: 3.2124883 | AR8: 4.0328871 | AS8: 27.231848 | AT8: 2.1114004 | AU8: 24.555588 | AV8: 32.534496 | AW8: 3.0080732 | AX8: 33.855616 | AY8: 7.2420135 | AZ8: 38.877145 | BA8: 3.2596916 | BB8: 36.619533 | BC8: 2.2113797 | BD8: 4.5475079 | BE8: 8.9384831 | BF8: 9.2022513 | BG8: 1.9418396 | BH8: 12.625287 | BI8: 13.317205 | BJ8: 6.5988198 | BK8: 33.959528 | BL8: 1.4143181 | BM8: 0.93677346 | BN8: 18.730995 | BO8: 2.0038155 | BP8: 4.0352386 | BQ8: 6.0234486 | BR8: 28.885364 | BS8: 2.1347228 | BT8: 4.5342685 | BU8: 14.365096 | BV8: 32.321705 | BW8: 11.126278 | BX8: 114.97004 | BY8: 56.683411 | BZ8: 38.282646 | CA8: 6.6731578 | CB8: 0.0097988089 | CC8: 8.4116393 | CD8: 27.61179 | CE8: 3.324354 | CF8: 1.300745 | CG8: 0.042275762 | CH8: 3.0158922 | CI8: 2.9802084 | CJ8: 2.5042926 | CK8: 10.183937 | CL8: 6.0525877 | CM8: 13.783617 | CN8: 50.195905 | CO8: 0 | CP8: 5.7306872 | CQ8: 11.993577 | CR8: 24.084701 | CS8: 17.092669 | CT8: 33.704955 | CU8: 45.806265 | CV8: 0.093370467 | CW8: 1.3509796 | CX8: 10.095662 | CY8: 0 | CZ8: 0.027007371 | DA8: 2.0044471 | DB8: 0.034589141 | DC8: 29.086086 | DD8: 4.0467075 | DE8: 3.9821681 | DF8: 5.4155008 | DG8: 0.53046049 | DH8: 11.112421 | DI8: 1.4883342 | DJ8: 35.221286 | DK8: 0 | DL8: 0.3208005 | DM8: 0.13411529 | DN8: 7.4018896 | DO8: 0 | DP8: 0.68848135 | DQ8: 29.379482 | DR8: 29.93991 | DS8: 0.11918583 | DT8: 14.627745 | DU8: 0 | DV8: 3.462154 | DW8: 50.692295 | DX8: 0.98154594 | DY8: 28.689201 | DZ8: 0 | EA8: 5.9050203 | EB8: 27.395656 | EC8: 4.3361565 | ED8: 0 | EE8: 1.2242302 | EF8: 2.1165992 | EG8: 7.7135193 | EH8: 0.71582814 | EI8: 5.9342082 | EJ8: 5.6735973 | EK8: 0 | EL8: 0.12830966 | EM8: 17.126788 | EN8: 1.9412046 | EO8: 3.3689603 | EP8: 0.021738653 | EQ8: 13.997382 | ER8: 0.0062099468 | ES8: 0.13478924 | ET8: 26.134358 | EU8: 8.4812053 | EV8: 10.988841 | EW8: 2.136262 | EX8: 14.370935 | EY8: 16.993043 | EZ8: 0.66693743 | FA8: 0 | FB8: 12.175918 | FC8: 0.39454251 | FD8: 0.12948293 | FE8: 0 | FF8: 0 | FG8: 0.91013721 | FH8: 0 | FI8: 0 | FJ8: 0.17699969 | FK8: 2.8725026 | FL8: 3.997474 | FM8: 50.662936 | FN8: 3.0450702 | FO8: 0.2070562 | FP8: 0 | FQ8: 0 | FR8: 5.7050269 | FS8: 13.01581 | FT8: 14.390395 | FU8: 0 | FV8: 4.5893436 | FW8: 15.244623 | FX8: 0 | FY8: 0 | FZ8: 0.98143108 | GA8: 1.8655087 | GB8: 0.003840943 | GC8: 1.4692657 | GD8: 0 | GE8: 0 | GF8: 0.26924756 | GG8: 15.177038 | GH8: 1.4395545 | GI8: 4.1622626 | GJ8: 0 | GK8: 0.013323251 | GL8: 3.8147152 | GM8: 0 | GN8: 10.017674 | GO8: 0 | GP8: 0 | GQ8: -4.3778549e-17 | GR8: 0 | GS8: 0.303396 | GT8: 3.6134448 | GU8: 3.9978443 | GV8: 0 | GW8: 0 | GX8: 0 | GY8: 0 | GZ8: 0.35079784 | HA8: 1.9996545 | HB8: 1.2140298 | HC8: 0 | HD8: 0 | HE8: 0 | HF8: 0 | HG8: 27.925506 | HH8: 0 | HI8: 0 | HJ8: 0 | HK8: 0.96209677 | HL8: 0 | HM8: 0.77824623 | HN8: 0 | HO8: 3.9986129 | HP8: 0.014017927 | HQ8: 0 | HR8: 0 | HS8: 0.46743061 | HT8: 7.0590041 | HU8: 0 | HV8: 0.57288454 | HW8: 0 | HX8: 0 | HY8: 5.796568 | HZ8: 0 | IA8: 12.093399 | IB8: 0 | IC8: 5.2464693 | ID8: 0 | IE8: 0 | IF8: 0.24382179 | IG8: 0 | IH8: 0.088742881 | II8: 0 | IJ8: 0.17622842 | IK8: 0.13117221 | IL8: 0.042026597 | IM8: 0 | IN8: 1.1016278 | IO8: 0 | IP8: 0 | IQ8: 2.4786128 | IR8: 0 | IS8: 0 | IT8: 0
A9: 6 | B9: 28.571858 | C9: 0.30657333 | D9: 1.9767586 | E9: 8.2832552 | F9: 8.6102106 | G9: 3.4093735 | H9: 22.089062 | I9: 23.485592 | J9: 6.1203972 | K9: 2.1198787 | L9: 56.268777 | M9: 10.170596 | N9: 1.859736 | O9: 11.869958 | P9: 119.11851 | Q9: 9.9984985 | R9: 20.986249 | S9: 2.2104678 | T9: 0.79860346 | U9: 1.9442984 | V9: 12.384452 | W9: 3.3439088 | X9: 8.9929004 | Y9: 31.949681 | Z9: 10.175027 | AA9: 38.21749 | AB9: 5.3557917 | AC9: 6.8253358 | AD9: 6.9151428 | AE9: 0.76830872 | AF9: 6.563683 | AG9: 4.2253315 | AH9: 27.127527 | AI9: 2.583644 | AJ9: 4.1347695 | AK9: 18.905042 | AL9: 6.0121346 | AM9: 4.1104367 | AN9: 0.3971187 | AO9: 2.2191916 | AP9: 23.39172 | AQ9: 6.8697006 | AR9: 7.3260152 | AS9: 6.0969125 | AT9: 2.6693149 | AU9: 15.53983 | AV9: 10.846873 | AW9: 0.1609766 | AX9: 6.9474874 | AY9: 3.0235507 | AZ9: 2.006807 | BA9: 0.00010914541 | BB9: 1.4376762 | BC9: 3.1801003 | BD9: 1.0786496 | BE9: 9.0813891 | BF9: 4.6201287 | BG9: 1.8507612 | BH9: 15.947816 | BI9: 2.8627327 | BJ9: 0.32135738 | BK9: 0.05609359 | BL9: 1.0051512 | BM9: 4.3283033 | BN9: 6.8125317 | BO9: 8.8429389 | BP9: 16.630823 | BQ9: 2.2275586 | BR9: 8.4530661 | BS9: 0.59283561 | BT9: 6.1463579 | BU9: 3.0242305 | BV9: 13.556458 | BW9: 0.6952729 | BX9: 24.663616 | BY9: 35.28264 | BZ9: 26.451461 | CA9: 13.969534 | CB9: 0.69098895 | CC9: 2.7188876 | CD9: 6.8598082 | CE9: 0.21157963 | CF9: 1.8612411 | CG9: 0.16862294 | CH9: 1.0781005 | CI9: 8.910924 | CJ9: 1.4463199 | CK9: 3.8199851 | CL9: 0.18331777 | CM9: 3.1260256 | CN9: 15.584079 | CO9: 0.11813401 | CP9: 1.1880489 | CQ9: 11.225606 | CR9: 4.2365691 | CS9: 10.103217 | CT9: 37.636165 | CU9: 22.717879 | CV9: 0.0034610221 | CW9: 3.0861807 | CX9: 0.98947244 | CY9: 0 | CZ9: 1.1386077 | DA9: 0.085259734 | DB9: 0.15351096 | DC9: 3.1207823 | DD9: 2.9354226 | DE9: 1.0201911 | DF9: 1.790236 | DG9: 7.6386241 | DH9: 3.0480729 | DI9: 0.2663626 | DJ9: 8.103497 | DK9: 5.8505627e-15 | DL9: 2.7690883e-06 | DM9: 0.12702148 | DN9: 0.84647181 | DO9: 0.022892238 | DP9: 0.11303213 | DQ9: 2.3471406 | DR9: 3.7201935 | DS9: -2.8524755e-19 | DT9: 5.5655833 | DU9: 0 | DV9: 5.6483016 | DW9: 3.4100095 | DX9: 1.9630919 | DY9: 3.6049344 | DZ9: 0 | EA9: 2.3300512 | EB9: 6.3295739 | EC9: 5.3587852 | ED9: 1.6212177 | EE9: 5.1738478 | EF9: 4.6920234 | EG9: 10.741873 | EH9: 0.062530246 | EI9: 16.795301 | EJ9: 1.7554474 | EK9: 5.59593 | EL9: 2.9661677 | EM9: 7.5685487 | EN9: 0.81947924 | EO9: 3.1516409 | EP9: 0.1314181 | EQ9: 0.99978624 | ER9: 0 | ES9: 0.46515094 | ET9: 5.9536914 | EU9: 0 | EV9: 1.2942825 | EW9: 6.0371154 | EX9: 6.6184987 | EY9: 0 | EZ9: 0.15202202 | FA9: 4.21453 | FB9: 5.4954307 | FC9: 1.4422985 | FD9: 1.9139168 | FE9: 0.035423841 | FF9: 0 | FG9: 0 | FH9: 0 | FI9: 0 | FJ9: 4.9334836 | FK9: 1.9150017 | FL9: 4.9968425 | FM9: 5.0664024 | FN9: 2.0522556 | FO9: 0.96489828 | FP9: 3.9184309 | FQ9: 4.7619608 | FR9: 0.98634681 | FS9: 4.1723274 | FT9: 0.41523885 | FU9: 0 | FV9: 4.2711538 | FW9: 0.71830535 | FX9: 0 | FY9: 0 | FZ9: 0.98143108 | GA9: 0.032926753 | GB9: 3.0897349 | GC9: 0.05437114 | GD9: 0 | GE9: 0.91648183 | GF9: 0 | GG9: 2.4638986 | GH9: 0 | GI9: 2.2310704 | GJ9: 0 | GK9: 0 | GL9: 1.3450578 | GM9: 0 | GN9: 3.9588247 | GO9: 0 | GP9: 0 | GQ9: 0 | GR9: 0.060505454 | GS9: 0.14453648 | GT9: 17.752117 | GU9: 0 | GV9: 6.9225343 | GW9: 0.78367181 | GX9: 0 | GY9: 0 | GZ9: 0 | HA9: 0.036344375 | HB9: 4.2059909 | HC9: 0 | HD9: 2.9087439 | HE9: 0 | HF9: 1.2883803 | HG9: 16.103851 | HH9: 0.96511174 | HI9: 0.84006765 | HJ9: 0.14679701 | HK9: 0 | HL9: 0 | HM9: 1.3905475 | HN9: 0 | HO9: 8.996879 | HP9: 0.99620949 | HQ9: 0 | HR9: 0.97054962 | HS9: 0 | HT9: 3.6473321 | HU9: 0 | HV9: 0 | HW9: 0 | HX9: 0 | HY9: 1.7540156 | HZ9: 0.94950168 | IA9: 15.001869 | IB9: 0 | IC9: 1.292506 | ID9: 0.01527992 | IE9: 0 | IF9: 0 | IG9: 0.3154027 | IH9: 0 | II9: 0 | IJ9: 0 | IK9: 0.8309164 | IL9: 0 | IM9: 0 | IN9: 0.29811427 | IO9: 0 | IP9: 0 | IQ9: 1.2340536 | IR9: 1.2360329 | IS9: 0 | IT9: 0
A10: 7 | B10: 118.7783 | C10: 5.1051911 | D10: 28.625336 | E10: 30.543309 | F10: 42.871796 | G10: 51.186527 | H10: 177.10848 | I10: 139.59746 | J10: 22.902023 | K10: 62.800113 | L10: 286.11451 | M10: 48.438257 | N10: 27.421178 | O10: 101.4263 | P10: 839.18785 | Q10: 43.554853 | R10: 58.951518 | S10: 44.267108 | T10: 44.169546 | U10: 30.052359 | V10: 113.52442 | W10: 7.9995826 | X10: 49.239305 | Y10: 219.06099 | Z10: 65.530004 | AA10: 173.52138 | AB10: 16.276385 | AC10: 28.941913 | AD10: 59.718591 | AE10: 45.987092 | AF10: 27.698897 | AG10: 31.865698 | AH10: 169.89498 | AI10: 38.953519 | AJ10: 13.143558 | AK10: 118.68617 | AL10: 48.755958 | AM10: 67.255364 | AN10: 9.6491877 | AO10: 13.222122 | AP10: 148.5273 | AQ10: 19.37779 | AR10: 9.0224079 | AS10: 92.015012 | AT10: 14.70862 | AU10: 11.867748 | AV10: 111.79733 | AW10: 4.5408693 | AX10: 97.471022 | AY10: 25.158467 | AZ10: 102.88617 | BA10: 17.954171 | BB10: 69.15901 | BC10: 15.412376 | BD10: 12.449779 | BE10: 50.807151 | BF10: 30.685267 | BG10: 9.209619 | BH10: 68.786389 | BI10: 30.524663 | BJ10: 24.124988 | BK10: 63.923817 | BL10: 5.751891 | BM10: 34.084259 | BN10: 61.532641 | BO10: 29.607168 | BP10: 114.52216 | BQ10: 9.9302093 | BR10: 62.862439 | BS10: 2.8728456 | BT10: 25.134636 | BU10: 19.140793 | BV10: 130.85265 | BW10: 49.394856 | BX10: 105.54203 | BY10: 72.910057 | BZ10: 140.56796 | CA10: 37.571984 | CB10: 35.833084 | CC10: 29.120521 | CD10: 111.85401 | CE10: 3.1691193 | CF10: 13.83162 | CG10: 10.585358 | CH10: 8.6810675 | CI10: 18.94859 | CJ10: 24.341447 | CK10: 5.5985919 | CL10: 16.261928 | CM10: 19.669417 | CN10: 38.447287 | CO10: 6.617437 | CP10: 11.164307 | CQ10: 17.925241 | CR10: 76.107192 | CS10: 145.04998 | CT10: 134.33116 | CU10: 166.72636 | CV10: 2.7557292 | CW10: 9.266573 | CX10: 12.868341 | CY10: 1.1279994 | CZ10: 0.13782159 | DA10: 1.8451423 | DB10: 3.9666617 | DC10: 21.406488 | DD10: 28.361387 | DE10: 11.027105 | DF10: 8.5042367 | DG10: 9.3525514 | DH10: 24.877362 | DI10: 8.5022851 | DJ10: 134.3404 | DK10: 0 | DL10: 1.783019 | DM10: 0.89745704 | DN10: 11.017129 | DO10: 10.012426 | DP10: 4.2469241 | DQ10: 41.640372 | DR10: 28.435945 | DS10: 14.79826 | DT10: 61.594648 | DU10: 6.5066485 | DV10: 44.199938 | DW10: 56.901387 | DX10: 26.323248 | DY10: 43.517715 | DZ10: 0.97093331 | EA10: 3.1752684 | EB10: 95.589415 | EC10: 1.4330358 | ED10: 3.2313262 | EE10: 8.027302 | EF10: 58.474035 | EG10: 22.075568 | EH10: 7.664153 | EI10: 26.833978 | EJ10: 7.0614062 | EK10: 23.747775 | EL10: 14.830839 | EM10: 79.52122 | EN10: 26.139812 | EO10: 40.833571 | EP10: 5.9836464 | EQ10: 35.031683 | ER10: 3.5662569 | ES10: 5.4423668 | ET10: 10.189902 | EU10: 9.1746034 | EV10: 0.35086105 | EW10: 2.9287023 | EX10: 34.122651 | EY10: 27.09667 | EZ10: 1.620179 | FA10: 4.9060229 | FB10: 59.596646 | FC10: 3.6400172 | FD10: 5.0713249 | FE10: 1.7198109 | FF10: 0 | FG10: 5.4608232 | FH10: 2.7432686 | FI10: 3.9996931 | FJ10: 12.825205 | FK10: 7.1372278 | FL10: 9.0140075 | FM10: 83.634136 | FN10: 19.918392 | FO10: 0.63846143 | FP10: 25.766847 | FQ10: 4.9680078 | FR10: 25.235067 | FS10: 16.068738 | FT10: 0.48967847 | FU10: 0 | FV10: 19.933674 | FW10: 44.094537 | FX10: 0 | FY10: 1.5348781 | FZ10: 2.1437935 | GA10: 0 | GB10: 13.026304 | GC10: 20.507839 | GD10: 0.090809309 | GE10: 0.005577014 | GF10: 1.2132436 | GG10: 59.828989 | GH10: 2.6011129 | GI10: 24.58767 | GJ10: 0 | GK10: 0 | GL10: 1.3241018 | GM10: 1.9477348 | GN10: 16.035688 | GO10: 0 | GP10: 0.69292802 | GQ10: 0.10287294 | GR10: 1.5624043 | GS10: 0.38293257 | GT10: 3.9416005 | GU10: 5.0292758 | GV10: 6.6156453 | GW10: 4.0111092 | GX10: 0.14718143 | GY10: 2.2339941 | GZ10: 2.1583239 | HA10: 2.9998645 | HB10: 9.3028393 | HC10: -1.5474376e-15 | HD10: 4.3123306 | HE10: 0 | HF10: 7.5523532 | HG10: 241.0823 | HH10: 3.2097637e-09 | HI10: 13.025988 | HJ10: 0 | HK10: 2.8862903 | HL10: 0.14864886 | HM10: 3.7252862 | HN10: -7.1332966e-17 | HO10: 34.053321 | HP10: 8.9658854 | HQ10: 4.9973451 | HR10: 2.0417694 | HS10: 2.1209415 | HT10: 17.255696 | HU10: 4.996166 | HV10: 0.49373679 | HW10: 2.9749961 | HX10: 6.7772558 | HY10: 14.005645 | HZ10: 0.94950168 | IA10: 31.00838 | IB10: 0 | IC10: 1.9049648 | ID10: 0.021531022 | IE10: 0.094115916 | IF10: 0 | IG10: 0.15659522 | IH10: 6.9804681 | II10: 0 | IJ10: 0 | IK10: 4.9854984 | IL10: 23.849854 | IM10: 3.4641016 | IN10: 0.10468572 | IO10: 180.99968 | IP10: 0 | IQ10: 11.293238 | IR10: 4.4408921e-16 | IS10: 19.026296 | IT10: 0
A11: 8 | B11: 52.61925 | C11: 1.1325078 | D11: 2.9674291 | E11: 32.557525 | F11: 23.14007 | G11: 7.2395022 | H11: 16.14636 | I11: 26.310179 | J11: 4.0057297 | K11: 18.634271 | L11: 97.359695 | M11: 3.1541312 | N11: 5.4719758 | O11: 40.49151 | P11: 374.02271 | Q11: 3.5212756 | R11: 13.805614 | S11: 14.25807 | T11: 5.5565584 | U11: 4.2528102 | V11: 28.261021 | W11: 4.7929326 | X11: 14.368982 | Y11: 23.150731 | Z11: 9.2805751 | AA11: 31.520711 | AB11: 4.1183653 | AC11: 5.0955861 | AD11: 9.4238381 | AE11: 2.3903747 | AF11: 6.2885761 | AG11: 7.2986287 | AH11: 76.949132 | AI11: 7.4875501 | AJ11: 6.8517249 | AK11: 22.886214 | AL11: 10.752763 | AM11: 5.2047496 | AN11: 3.0666308 | AO11: 8.9907776 | AP11: 28.733223 | AQ11: 8.2029776 | AR11: 1.7701907 | AS11: 14.003673 | AT11: 1.2430281 | AU11: 13.138077 | AV11: 17.9675 | AW11: 1.3299031 | AX11: 9.9728523 | AY11: 5.5434359 | AZ11: 22.367021 | BA11: 4.2300887 | BB11: 21.031088 | BC11: 2.7325395 | BD11: 6.4499663 | BE11: 3.0290509 | BF11: 3.2617411 | BG11: 1.6980855 | BH11: 13.134784 | BI11: 3.1326686 | BJ11: 4.3869719 | BK11: 0.99880964 | BL11: 0.37896345 | BM11: 23.689283 | BN11: 17.318891 | BO11: 5.9952671 | BP11: 4.1097145 | BQ11: 4.1745933 | BR11: 5.3627642 | BS11: 0.45577124 | BT11: 8.4777366 | BU11: 4.6013443 | BV11: 17.84907 | BW11: 8.220519 | BX11: 42.757097 | BY11: 12.776513 | BZ11: 14.484706 | CA11: 5.6285991 | CB11: 0.046962256 | CC11: 8.9265733 | CD11: 12.190771 | CE11: 0.38823182 | CF11: 4.0472588 | CG11: 0.089993182 | CH11: 2.5657062 | CI11: 8.0607234 | CJ11: 0.10650728 | CK11: 1.7259663 | CL11: 1.0039748 | CM11: 4.0515821 | CN11: 29.756652 | CO11: 2.8885751 | CP11: 2.294282 | CQ11: 5.2827849 | CR11: 34.206579 | CS11: 7.4221752 | CT11: 14.408651 | CU11: 60.968428 | CV11: 1.1584712 | CW11: 1.8582169 | CX11: 0.0030591216 | CY11: 4.2481354e-18 | CZ11: 0 | DA11: 0.19207182 | DB11: 0.14513378 | DC11: 2.9866169 | DD11: 1.0868684 | DE11: 4.9777101 | DF11: 0 | DG11: 14.885791 | DH11: 7.9953109 | DI11: 1.9369466 | DJ11: 6.0823417 | DK11: 1.6837601 | DL11: 0.2002544 | DM11: 0.075681179 | DN11: 6.6129359 | DO11: 5.9136797 | DP11: 1.0420458 | DQ11: 6.8355271 | DR11: 1.3642059 | DS11: 5.0961004 | DT11: 14.300969 | DU11: 0.0037750482 | DV11: 2.972168 | DW11: 6.4800705 | DX11: 7.8523676 | DY11: 15.933079 | DZ11: 1.9823959 | EA11: 4.3920252 | EB11: 7.6491272 | EC11: 0.79346318 | ED11: 0 | EE11: 1.282885 | EF11: 3.3451368 | EG11: 5.2490469 | EH11: 5.5823359 | EI11: 3.1992649 | EJ11: 0 | EK11: 3.8838076 | EL11: 3.9598936 | EM11: 17.496252 | EN11: 0.11451844 | EO11: 12.762923 | EP11: 0.1474215 | EQ11: 3.0153989 | ER11: 0.13918118 | ES11: 0.18387617 | ET11: 2.5664171 | EU11: 3.2353551 | EV11: 1.1595967 | EW11: 3.9049364 | EX11: 14.038329 | EY11: 5.9822532 | EZ11: 1.2810793 | FA11: 0.28984238 | FB11: 10.012614 | FC11: 1.4885142 | FD11: 0 | FE11: 0.18758808 | FF11: 0 | FG11: 0 | FH11: 0.43192087 | FI11: 0 | FJ11: 1.6877183 | FK11: 0.96474723 | FL11: 4.9968425 | FM11: 9.2350745 | FN11: 3.9999823 | FO11: 0 | FP11: 0 | FQ11: 0.32353594 | FR11: 2.2304579 | FS11: 2.3024525 | FT11: 3.0365864 | FU11: 0 | FV11: 0 | FW11: 14.954982 | FX11: 0 | FY11: 0 | FZ11: 0 | GA11: 0.33061932 | GB11: 0 | GC11: 0.7659121 | GD11: 0 | GE11: 0 | GF11: 0 | GG11: 10.183926 | GH11: 0 | GI11: 0.82642909 | GJ11: 0 | GK11: 0 | GL11: 0 | GM11: 1.9477348 | GN11: 11.921747 | GO11: 0 | GP11: 0.40903956 | GQ11: 0 | GR11: 0 | GS11: 0 | GT11: 0.32737933 | GU11: 1.9989222 | GV11: 1.9741135 | GW11: 0.24582733 | GX11: 0 | GY11: 0.0094534433 | GZ11: 0 | HA11: 0 | HB11: 0 | HC11: 0 | HD11: 0 | HE11: 0 | HF11: 0 | HG11: 28.920885 | HH11: 0 | HI11: 0.91780434 | HJ11: 0 | HK11: -5.9893424e-17 | HL11: 0.043866831 | HM11: 0.23053474 | HN11: 0 | HO11: 1.0127734 | HP11: 1.0060968 | HQ11: 1.998938 | HR11: 1.0712198 | HS11: 3.2434229 | HT11: 1.46014 | HU11: 0.98205308 | HV11: 0 | HW11: 0 | HX11: 0 | HY11: 1.4065726 | HZ11: 7.7065902e-18 | IA11: 5.0103249 | IB11: 0 | IC11: 1.06465 | ID11: 0 | IE11: 0 | IF11: 0 | IG11: 1.0964698e-18 | IH11: 1.9944195 | II11: 0 | IJ11: 0 | IK11: 0.0061610511 | IL11: 0 | IM11: 0 | IN11: 1.1016278 | IO11: 0 | IP11: 0.00058813294 | IQ11: 4.9453218 | IR11: 4.1025797 | IS11: 0 | IT11: 0
A12: 9 | B12: 339.42386 | C12: 11.2827 | D12: 71.252656 | E12: 61.225513 | F12: 197.27114 | G12: 52.717053 | H12: 101.41025 | I12: 316.43375 | J12: 37.10455 | K12: 89.552853 | L12: 495.20198 | M12: 152.6186 | N12: 75.713901 | O12: 131.56046 | P12: 1674.6148 | Q12: 122.51757 | R12: 90.669568 | S12: 55.950166 | T12: 23.450521 | U12: 141.95362 | V12: 213.87614 | W12: 14.58708 | X12: 83.050979 | Y12: 307.16552 | Z12: 161.92878 | AA12: 511.6289 | AB12: 36.175069 | AC12: 72.502295 | AD12: 107.45517 | AE12: 77.745656 | AF12: 78.944025 | AG12: 108.5321 | AH12: 275.18271 | AI12: 43.511061 | AJ12: 26.92357 | AK12: 349.53829 | AL12: 200.37073 | AM12: 73.873992 | AN12: 17.711664 | AO12: 12.086937 | AP12: 261.71155 | AQ12: 43.908323 | AR12: 122.59767 | AS12: 69.827427 | AT12: 38.010501 | AU12: 62.202402 | AV12: 138.09862 | AW12: 15.057709 | AX12: 84.644393 | AY12: 41.694628 | AZ12: 204.9583 | BA12: 26.075584 | BB12: 156.21157 | BC12: 18.618312 | BD12: 295.52004 | BE12: 50.756001 | BF12: 71.82299 | BG12: 102.08926 | BH12: 57.338981 | BI12: 47.187504 | BJ12: 42.327044 | BK12: 54.079131 | BL12: 13.511534 | BM12: 209.8453 | BN12: 58.585189 | BO12: 59.532737 | BP12: 138.57243 | BQ12: 50.878279 | BR12: 122.89046 | BS12: 3.9610192 | BT12: 64.386935 | BU12: 31.618551 | BV12: 178.35642 | BW12: 102.56153 | BX12: 178.5729 | BY12: 177.08365 | BZ12: 247.19361 | CA12: 74.537768 | CB12: 10.244414 | CC12: 51.532335 | CD12: 158.544 | CE12: 6.7455357 | CF12: 1.7720187 | CG12: 27.197156 | CH12: 15.911954 | CI12: 30.421012 | CJ12: 21.656637 | CK12: 24.106709 | CL12: 52.68667 | CM12: 101.28579 | CN12: 119.50263 | CO12: 1.0513325 | CP12: 26.516903 | CQ12: 70.279292 | CR12: 136.30987 | CS12: 21.664617 | CT12: 189.24456 | CU12: 245.05426 | CV12: 0.88361406 | CW12: 18.810675 | CX12: 25.953261 | CY12: 0.063573958 | CZ12: 0.013602731 | DA12: 21.789267 | DB12: 36.855866 | DC12: 66.360714 | DD12: 130.13138 | DE12: 11.111488 | DF12: 11.076551 | DG12: 10.944116 | DH12: 63.311323 | DI12: 22.541357 | DJ12: 372.69848 | DK12: 14.108394 | DL12: 3.3010565 | DM12: 4.3612166 | DN12: 20.746136 | DO12: 10.20144 | DP12: 5.7824256 | DQ12: 47.996784 | DR12: 33.688475 | DS12: 18.245316 | DT12: 62.340993 | DU12: 24.777737 | DV12: 122.10002 | DW12: 60.343135 | DX12: 20.629157 | DY12: 54.303348 | DZ12: 0 | EA12: 3.3435429 | EB12: 95.76171 | EC12: 13.902398 | ED12: 8.5374381 | EE12: 24.821271 | EF12: 356.42173 | EG12: 26.404211 | EH12: 6.4782373 | EI12: 58.428589 | EJ12: 18.97201 | EK12: 36.824066 | EL12: 10.529246 | EM12: 147.01454 | EN12: 10.487299 | EO12: 132.52179 | EP12: 0.90603019 | EQ12: 114.0452 | ER12: 0.25428891 | ES12: 1.8571436 | ET12: 74.355699 | EU12: 13.073146 | EV12: 5.009149 | EW12: 5.0605169 | EX12: 120.90435 | EY12: 32.183921 | EZ12: 2.9476598 | FA12: 20.26319 | FB12: 110.99661 | FC12: 5.7855573 | FD12: 8.9240277 | FE12: 6.484372 | FF12: -5.162192e-17 | FG12: 1.8222994 | FH12: 1.641501 | FI12: 0.011095356 | FJ12: 31.406388 | FK12: 55.840676 | FL12: 36.976634 | FM12: 38.782716 | FN12: 36.549303 | FO12: 3.327676 | FP12: 11.777712 | FQ12: 8.5627792 | FR12: 24.973134 | FS12: 18.651762 | FT12: 21.959077 | FU12: 1.355924e-18 | FV12: 30.647901 | FW12: 47.049652 | FX12: 0 | FY12: 3.9162721 | FZ12: 16.450501 | GA12: 2.1232687 | GB12: 29.436092 | GC12: 3.1478014 | GD12: 2.180957 | GE12: 2.4040147e-05 | GF12: 2.3724016 | GG12: 77.067886 | GH12: 10.598723 | GI12: 20.832001 | GJ12: 0 | GK12: 4.4809675 | GL12: 11.68036 | GM12: 18.556817 | GN12: 39.881063 | GO12: 0.60432468 | GP12: 0.7085118 | GQ12: 0.55155494 | GR12: 0.15275379 | GS12: 4.3990818 | GT12: 45.370625 | GU12: 27.007482 | GV12: 9.6090523 | GW12: 41.509414 | GX12: 0.39016464 | GY12: 1.2559467 | GZ12: 2.5731108 | HA12: 6.0175825 | HB12: 20.419993 | HC12: 0 | HD12: 0.03818583 | HE12: 12.830959 | HF12: 6.4133766 | HG12: 292.3479 | HH12: 13.51306 | HI12: 23.640682 | HJ12: 3.3988739 | HK12: 0.96673908 | HL12: 0.1755733 | HM12: 12.437227 | HN12: 0 | HO12: 82.991021 | HP12: 12.950723 | HQ12: 44.007549 | HR12: 5.4079613 | HS12: 16.547564 | HT12: 49.020133 | HU12: 1.0781563 | HV12: 1.1457691 | HW12: 15.127715 | HX12: 1.3299148e-14 | HY12: 28.9787 | HZ12: 10.038558 | IA12: 140.15241 | IB12: 3.4680746 | IC12: 12.764224 | ID12: 3.4856506 | IE12: 0.069626983 | IF12: 0 | IG12: 4.3441171 | IH12: 26.954244 | II12: 0 | IJ12: 5.9196472 | IK12: 2.4927492 | IL12: 8.1816822 | IM12: 0 | IN12: 7.5193326 | IO12: 13.001096 | IP12: 16.212219 | IQ12: 41.878478 | IR12: 0 | IS12: -6.0084442e-16 | IT12: 0
A13: 10 | B13: 106.90674 | C13: 5.7594264 | D13: 11.321145 | E13: 22.924158 | F13: 28.019765 | G13: 23.857215 | H13: 83.685322 | I13: 111.76221 | J13: 9.4789146 | K13: 14.967876 | L13: 221.00748 | M13: 15.749921 | N13: 16.267412 | O13: 62.866065 | P13: 465.86955 | Q13: 32.63214 | R13: 43.039748 | S13: 9.1964251 | T13: 9.2674619 | U13: 25.504823 | V13: 36.764353 | W13: 10.841209 | X13: 24.76378 | Y13: 133.04162 | Z13: 23.85613 | AA13: 134.2232 | AB13: 10.065942 | AC13: 30.511796 | AD13: 19.835177 | AE13: 21.350278 | AF13: 32.694573 | AG13: 39.964673 | AH13: 158.85828 | AI13: 31.694923 | AJ13: 12.013665 | AK13: 182.29964 | AL13: 27.307064 | AM13: 19.15616 | AN13: 3.6460463 | AO13: 10.936488 | AP13: 75.807438 | AQ13: 5.0432707 | AR13: 4.0278867 | AS13: 35.411288 | AT13: 4.5242886 | AU13: 14.721434 | AV13: 43.15629 | AW13: 3.0694449 | AX13: 49.908484 | AY13: 11.365061 | AZ13: 56.916815 | BA13: 13.242668 | BB13: 23.104476 | BC13: 9.0104767 | BD13: 22.899569 | BE13: 58.620678 | BF13: 20.440686 | BG13: 4.9750375 | BH13: 69.54355 | BI13: 17.005565 | BJ13: 5.7856209 | BK13: 5.0470259 | BL13: 5.8806097 | BM13: 56.659543 | BN13: 41.954988 | BO13: 5.6525921 | BP13: 55.073051 | BQ13: 12.63702 | BR13: 39.39682 | BS13: 0.19893314 | BT13: 17.929327 | BU13: 6.3129843 | BV13: 26.332204 | BW13: 6.3730552 | BX13: 65.087997 | BY13: 46.068764 | BZ13: 52.751456 | CA13: 41.095629 | CB13: 0.65042316 | CC13: 32.171514 | CD13: 41.672383 | CE13: 4.3790655 | CF13: 3.3796998 | CG13: 1.9244621 | CH13: 2.8399797 | CI13: 4.4700156 | CJ13: 5.7884317 | CK13: 5.3056782 | CL13: 89.380393 | CM13: 9.4348675 | CN13: 24.350325 | CO13: 3.9664198 | CP13: 2.8657792 | CQ13: 23.234907 | CR13: 25.930578 | CS13: 65.674718 | CT13: 59.662397 | CU13: 101.12361 | CV13: 1.2347237 | CW13: 17.754509 | CX13: 4.9473622 | CY13: 0.024862067 | CZ13: 106.07609 | DA13: 5.9248359 | DB13: 3.5200326 | DC13: 9.7648981 | DD13: 5.2418558 | DE13: 14.049838 | DF13: 3.0851123 | DG13: 33.073664 | DH13: 7.428842 | DI13: 1.2262597 | DJ13: 50.413623 | DK13: 0.0021009292 | DL13: 1.9170671 | DM13: 4.3017652 | DN13: 21.429291 | DO13: 0.98561329 | DP13: 3.2948461 | DQ13: 33.047337 | DR13: 5.6248007 | DS13: 17.174493 | DT13: 11.355991 | DU13: 8.8544572 | DV13: 26.224009 | DW13: 25.604134 | DX13: 2.0130417 | DY13: 21.329658 | DZ13: 0 | EA13: 1.2115342 | EB13: 30.054945 | EC13: 3.3716642 | ED13: 0.52497424 | EE13: 9.8472927 | EF13: 14.772859 | EG13: 15.823758 | EH13: 5.6826146 | EI13: 39.685243 | EJ13: 0.994295 | EK13: 18.095297 | EL13: 2.534672 | EM13: 25.847069 | EN13: 13.629881 | EO13: 17.610406 | EP13: 3.0958515 | EQ13: 14.996794 | ER13: 0.012227812 | ES13: 3.9499367 | ET13: 14.205187 | EU13: 2.9747802 | EV13: 0.36374149 | EW13: 6.8961535 | EX13: 33.919314 | EY13: 19.039657 | EZ13: 0.15980255 | FA13: 1.1709577 | FB13: 12.636875 | FC13: 0.48706701 | FD13: 0.95695842 | FE13: 0.2561344 | FF13: 0 | FG13: 0.98870009 | FH13: 3.9752841 | FI13: 0 | FJ13: 2.1527911 | FK13: 3.3656972 | FL13: 7.994948 | FM13: 16.873884 | FN13: 6.0916518 | FO13: 0.057059431 | FP13: 0.97960774 | FQ13: 0.48932309 | FR13: 17.978309 | FS13: 12.189179 | FT13: 6.8645179 | FU13: 73.999953 | FV13: 7.9257543 | FW13: 5.5324708 | FX13: 0 | FY13: 3.8574669 | FZ13: 0.98143108 | GA13: 11.360529 | GB13: 2.8282058 | GC13: 0.6705623 | GD13: 0 | GE13: 12.595238 | GF13: 1.1830047 | GG13: 19.702462 | GH13: 0.82070494 | GI13: 6.6415498 | GJ13: 0 | GK13: 0 | GL13: 4.4662028 | GM13: 0.97386739 | GN13: 20.783829 | GO13: 0 | GP13: 0.1976454 | GQ13: 0.046251918 | GR13: 2.154291 | GS13: 0.9726222 | GT13: 12.225081 | GU13: 6.0580328 | GV13: 3.9981849 | GW13: 15.578401 | GX13: 0.98545501 | GY13: 0.017963865 | GZ13: 0 | HA13: 3.0001516 | HB13: 5.4322562 | HC13: -1.8793105e-16 | HD13: 0.96958129 | HE13: 0.63865531 | HF13: 3.7689521 | HG13: 144.60442 | HH13: 0 | HI13: 4.6853634 | HJ13: 0 | HK13: 0.46335754 | HL13: 0.03409674 | HM13: 3.6929913 | HN13: 0 | HO13: 10.017581 | HP13: 7.9696759 | HQ13: 0.0015800573 | HR13: 0.97054962 | HS13: 4.6127017 | HT13: 13.358668 | HU13: 0.98205308 | HV13: 0 | HW13: 5.0135769 | HX13: 0 | HY13: 2.3925198 | HZ13: 7.5960135 | IA13: 7.0432268 | IB13: 0 | IC13: 0.46155444 | ID13: 4.9052306 | IE13: 0.12454337 | IF13: 0 | IG13: 0 | IH13: 0.99773598 | II13: 0 | IJ13: 1.960983 | IK13: 2.6184508 | IL13: 2.9694031 | IM13: 7.6555103e-15 | IN13: 1.7866198 | IO13: 2.9999947 | IP13: 0.001589842 | IQ13: 8.7725191 | IR13: 0 | IS13: 0 | IT13: 0
A14: 11 | B14: 448.25916 | C14: 21.547138 | D14: 72.293706 | E14: 74.190908 | F14: 138.90734 | G14: 70.752955 | H14: 275.29694 | I14: 460.86241 | J14: 67.09809 | K14: 110.13588 | L14: 963.50621 | M14: 152.0314 | N14: 95.176393 | O14: 124.9857 | P14: 2032.6497 | Q14: 76.364814 | R14: 211.60911 | S14: 119.07477 | T14: 102.74757 | U14: 84.58106 | V14: 196.39489 | W14: 27.799392 | X14: 61.180648 | Y14: 322.38297 | Z14: 96.839922 | AA14: 324.39487 | AB14: 47.354059 | AC14: 106.98821 | AD14: 118.94224 | AE14: 161.17361 | AF14: 95.028832 | AG14: 97.876952 | AH14: 502.48913 | AI14: 73.097659 | AJ14: 61.530225 | AK14: 402.03651 | AL14: 128.86972 | AM14: 50.512833 | AN14: 30.234621 | AO14: 65.095713 | AP14: 285.22191 | AQ14: 33.888737 | AR14: 76.384061 | AS14: 167.0436 | AT14: 28.575761 | AU14: 92.193763 | AV14: 191.93403 | AW14: 21.98497 | AX14: 157.7644 | AY14: 92.23682 | AZ14: 169.32032 | BA14: 45.874075 | BB14: 54.855365 | BC14: 39.098405 | BD14: 66.993151 | BE14: 67.286844 | BF14: 90.39806 | BG14: 29.002847 | BH14: 155.94968 | BI14: 41.550953 | BJ14: 36.188563 | BK14: 132.29558 | BL14: 20.627751 | BM14: 285.14308 | BN14: 131.86137 | BO14: 44.426523 | BP14: 110.43473 | BQ14: 25.899469 | BR14: 106.73577 | BS14: 3.6310159 | BT14: 95.483385 | BU14: 57.626166 | BV14: 92.859457 | BW14: 66.753385 | BX14: 226.24213 | BY14: 255.22542 | BZ14: 237.57537 | CA14: 141.5951 | CB14: 10.101447 | CC14: 105.80231 | CD14: 177.77937 | CE14: 34.598392 | CF14: 44.223442 | CG14: 46.620415 | CH14: 51.824795 | CI14: 30.445489 | CJ14: 18.573716 | CK14: 17.58589 | CL14: 28.673263 | CM14: 56.351016 | CN14: 63.229329 | CO14: 5.6379766 | CP14: 22.808709 | CQ14: 72.844457 | CR14: 134.68191 | CS14: 355.14789 | CT14: 169.0051 | CU14: 326.99985 | CV14: 23.472754 | CW14: 16.841777 | CX14: 36.38521 | CY14: 18.041891 | CZ14: 0.070356055 | DA14: 6.4624698 | DB14: 2.5497314 | DC14: 105.67026 | DD14: 17.156393 | DE14: 37.149481 | DF14: 20.842532 | DG14: 101.94605 | DH14: 63.415156 | DI14: 32.080186 | DJ14: 165.32031 | DK14: 0.12701351 | DL14: 28.354096 | DM14: 1.2493175 | DN14: 25.876783 | DO14: 1.6033252 | DP14: 8.7653462 | DQ14: 79.372296 | DR14: 25.581083 | DS14: 63.233596 | DT14: 110.8584 | DU14: 28.555461 | DV14: 79.622239 | DW14: 71.14161 | DX14: 4.9077297 | DY14: 86.958136 | DZ14: 5.2381032 | EA14: 28.687851 | EB14: 167.84107 | EC14: 22.808694 | ED14: 25.334995 | EE14: 15.178455 | EF14: 16.14087 | EG14: 68.346596 | EH14: 16.387224 | EI14: 45.739417 | EJ14: 21.857581 | EK14: 24.691825 | EL14: 23.74071 | EM14: 215.06602 | EN14: 16.239168 | EO14: 78.924296 | EP14: 51.260421 | EQ14: 96.992735 | ER14: 17.480768 | ES14: 11.731434 | ET14: 31.794028 | EU14: 22.367095 | EV14: 1.2681653 | EW14: 13.880809 | EX14: 109.9416 | EY14: 53.995333 | EZ14: 5.3063695 | FA14: 18.900326 | FB14: 150.50071 | FC14: 1.1406844 | FD14: 6.8967466 | FE14: 1.7198109 | FF14: 5 | FG14: 2.6744383 | FH14: 2.3484326 | FI14: 68.000289 | FJ14: 29.696847 | FK14: 50.897031 | FL14: 13.026815 | FM14: 83.717109 | FN14: 52.637818 | FO14: 4.8244914 | FP14: 11.561051 | FQ14: 9.3512825 | FR14: 51.351935 | FS14: 24.307587 | FT14: 2.0492885 | FU14: 2.6871409e-18 | FV14: 27.073139 | FW14: 75.361721 | FX14: 0 | FY14: 3.1754596 | FZ14: 12.981461 | GA14: 8.5949595 | GB14: 20.9813 | GC14: 12.840496 | GD14: 0.96106307 | GE14: 0.016310489 | GF14: 3.2374913 | GG14: 154.97669 | GH14: 11.198265 | GI14: 21.625879 | GJ14: 0 | GK14: 0.46622533 | GL14: 9.9460132 | GM14: 39.954391 | GN14: 49.387168 | GO14: 2.3750281 | GP14: 2.1968927 | GQ14: 7.9978995 | GR14: 0.59224918 | GS14: 4.1693173 | GT14: 24.156467 | GU14: 15.991377 | GV14: 22.044102 | GW14: 31.013699 | GX14: 3.0636814 | GY14: 0.56789649 | GZ14: 0.70159569 | HA14: 9.9982724 | HB14: 9.3483908 | HC14: 1.4292248e-15 | HD14: 1.5401376 | HE14: 0.016713105 | HF14: 29.548128 | HG14: 368.69581 | HH14: 80.235757 | HI14: 22.772008 | HJ14: 1.8513478 | HK14: 1.8680703 | HL14: 59.038384 | HM14: 4.0795203 | HN14: 6 | HO14: 63.038392 | HP14: 31.086132 | HQ14: 6.1372382 | HR14: 2.1424395 | HS14: 27.69328 | HT14: 48.52431 | HU14: 1.0151985 | HV14: 2.2440454 | HW14: 3.9666614 | HX14: -1.4985375e-19 | HY14: 38.324176 | HZ14: 16.318933 | IA14: 57.105233 | IB14: 0.35344759 | IC14: 7.6055914 | ID14: 0 | IE14: 9.9749837 | IF14: 0 | IG14: 21.791371 | IH14: 18.000172 | II14: 0 | IJ14: 6.5472369 | IK14: 7.5279654 | IL14: 5.1068653 | IM14: 7.6555103e-15 | IN14: 5.6537713 | IO14: 12.010858 | IP14: 0.0073225473 | IQ14: 9.9817971 | IR14: 0 | IS14: 2.9504469e-18 | IT14: 0
... A34: 31 | B34: 128.18631 | C34: 5.7959954 | D34: 28.118465 | E34: 46.979981 | F34: 47.557284 | G34: 48.861726 | H34: 128.45737 | I34: 138.70026 | J34: 27.938995 | K34: 54.122061 | L34: 340.13205 | M34: 48.963905 | N34: 35.336747 | O34: 85.738458 | P34: 1097.0339 | Q34: 36.723254 | R34: 68.076006 | S34: 55.760439 | T34: 51.500805 | U34: 30.327904 | V34: 121.704 | W34: 12.835278 | X34: 49.26392 | Y34: 216.18937 | Z34: 61.710928 | AA34: 205.89404 | AB34: 29.478139 | AC34: 28.93868 | AD34: 64.057279 | AE34: 38.690046 | AF34: 25.087881 | AG34: 33.652223 | AH34: 235.64082 | AI34: 33.51922 | AJ34: 12.232579 | AK34: 134.72522 | AL34: 68.610517 | AM34: 44.071014 | AN34: 7.5470947 | AO34: 14.619661 | AP34: 111.0738 | AQ34: 24.900298 | AR34: 18.146339 | AS34: 77.792565 | AT34: 14.961258 | AU34: 18.948677 | AV34: 140.84492 | AW34: 4.3399643 | AX34: 86.381088 | AY34: 21.210762 | AZ34: 101.12205 | BA34: 12.829634 | BB34: 85.142732 | BC34: 14.611344 | BD34: 16.5759 | BE34: 50.857624 | BF34: 39.034938 | BG34: 7.2375927 | BH34: 118.09104 | BI34: 25.605432 | BJ34: 26.954728 | BK34: 61.926197 | BL34: 11.277518 | BM34: 48.488942 | BN34: 66.851546 | BO34: 35.744057 | BP34: 79.827987 | BQ34: 10.688619 | BR34: 75.612271 | BS34: 0.93247977 | BT34: 37.099055 | BU34: 17.889192 | BV34: 201.34743 | BW34: 46.342353 | BX34: 109.06934 | BY34: 69.879234 | BZ34: 144.01362 | CA34: 45.189963 | CB34: 36.877266 | CC34: 34.285531 | CD34: 107.19621 | CE34: 2.0759139 | CF34: 8.1017482 | CG34: 10.329036 | CH34: 5.4031604 | CI34: 19.009046 | CJ34: 14.484784 | CK34: 4.8878829 | CL34: 16.063489 | CM34: 40.107596 | CN34: 35.780527 | CO34: 6.8545437 | CP34: 9.4106849 | CQ34: 25.83078 | CR34: 79.696053 | CS34: 22.852795 | CT34: 117.62825 | CU34: 159.17837 | CV34: 0.93872128 | CW34: 7.925776 | CX34: 19.007486 | CY34: 1.0584988 | CZ34: 0.067663483 | DA34: 7.6314024 | DB34: 3.1136194 | DC34: 20.743992 | DD34: 21.865224 | DE34: 9.1693017 | DF34: 10.167721 | DG34: 9.5286575 | DH34: 29.974372 | DI34: 4.8773768 | DJ34: 108.8612 | DK34: 0.16026805 | DL34: 1.354208 | DM34: 0.82177586 | DN34: 9.3260333 | DO34: 8.5648945 | DP34: 5.4157159 | DQ34: 34.437448 | DR34: 22.394503 | DS34: 19.858487 | DT34: 69.847605 | DU34: 2.178686 | DV34: 39.514759 | DW34: 55.791485 | DX34: 29.446378 | DY34: 43.780518 | DZ34: 0 | EA34: 9.2277705 | EB34: 99.043125 | EC34: 0.23726789 | ED34: 7.6365048 | EE34: 5.8333864 | EF34: 111.71626 | EG34: 22.977854 | EH34: 4.3854631 | EI34: 44.033122 | EJ34: 6.7350137 | EK34: 24.519191 | EL34: 1.9774452 | EM34: 83.949207 | EN34: 17.773536 | EO34: 31.685284 | EP34: 0.75886501 | EQ34: 16.034051 | ER34: 9.0202112 | ES34: 3.3474975 | ET34: 14.784771 | EU34: 9.7495461 | EV34: 0.33625095 | EW34: 9.7623411 | EX34: 44.080558 | EY34: 21.336311 | EZ34: 1.9475882 | FA34: 8.8885265 | FB34: 69.423703 | FC34: 3.8413846 | FD34: 5.8988004 | FE34: 0.85990544 | FF34: 0 | FG34: 5.855592 | FH34: 1.8573943 | FI34: 0 | FJ34: 3.1264606 | FK34: 6.9874964 | FL34: 11.024374 | FM34: 79.470069 | FN34: 18.118892 | FO34: 0.46395372 | FP34: 16.818767 | FQ34: 5.62018 | FR34: 14.362243 | FS34: 16.710878 | FT34: 2.0129435 | FU34: 9.3291719e-20 | FV34: 13.178809 | FW34: 59.424133 | FX34: 0 | FY34: 2.0147602 | FZ34: 1.2831718 | GA34: 0.99197987 | GB34: 12.936203 | GC34: 18.014897 | GD34: 0.0028594477 | GE34: 0.005870697 | GF34: 0.089070456 | GG34: 57.719207 | GH34: 2.7167325 | GI34: 18.802666 | GJ34: -4.2445123e-16 | GK34: 1.0864453 | GL34: 2.7269987 | GM34: 2.4282537 | GN34: 20.047528 | GO34: 0.70761473 | GP34: 0 | GQ34: 0.87762148 | GR34: 0.42596857 | GS34: 0.73431958 | GT34: 4.7633631 | GU34: 11.026042 | GV34: 6.3383234 | GW34: 2.0696094 | GX34: 7.8988249 | GY34: 0.83395697 | GZ34: 0.80114224 | HA34: 0 | HB34: 9.5409821 | HC34: -9.6252302e-16 | HD34: 7.1973017 | HE34: 0 | HF34: 5.0926109 | HG34: 277.02099 | HH34: 0.034703626 | HI34: 10.909361 | HJ34: 0.92567392 | HK34: 2.073391 | HL34: 0.17546732 | HM34: 3.8635636 | HN34: -7.1332966e-17 | HO34: 12.039901 | HP34: 10.198641 | HQ34: 5.9968141 | HR34: 8.6570202 | HS34: 1.4351967 | HT34: 28.159994 | HU34: 5.8923185 | HV34: 0 | HW34: 2.9749961 | HX34: 0 | HY34: 17.365771 | HZ34: 5.9340155 | IA34: 51.08976 | IB34: 0.35344759 | IC34: 2.5522008 | ID34: 5.8862767 | IE34: 0 | IF34: 0 | IG34: 1.2395677 | IH34: 2.9916292 | II34: 8.0375976 | IJ34: 0 | IK34: 1.6618328 | IL34: 9.992639 | IM34: 0 | IN34: 0.40227321 | IO34: 100.99982 | IP34: 0 | IQ34: 21.616262 | IR34: 0 | IS34: 0.052996805 | IT34: 0
B37: =IF(COUNTIF(Topic_importance!$A$2:$A$21,'Result 1'!B2),1,0) -> 1 | C37: =IF(COUNTIF(Topic_importance!$A$2:$A$21,'Result 1'!C2),1,0) -> 0 | D37: =IF(COUNTIF(Topic_importance!$A$2:$A$21,'Result 1'!D2),1,0) -> 0 | E37: =IF(COUNTIF(Topic_importance!$A$2:$A$21,'Result 1'!E2),1,0) -> 0 | F37: =IF(COUNTIF(Topic_importance!$A$2:$A$21,'Result 1'!F2),1,0) -> 0 | G37: =IF(COUNTIF(Topic_importance!$A$2:$A$21,'Result 1'!G2),1,0) -> 0 | H37: =IF(COUNTIF(Topic_importance!$A$2:$A$21,'Result 1'!H2),1,0) -> 1 | I37: =IF(COUNTIF(Topic_importance!$A$2:$A$21,'Result 1'!I2),1,0) -> 1 | ... IT37: =IF(COUNTIF(Topic_importance!$A$2:$A$21,'Result 1'!IT2),1,0) -> 0
A42: {=TRANSPOSE(A1:IT37)} -> C1 | B42: document | C42: 0 | D42: 1 | E42: 2 | F42: 3 | G42: 4 | H42: 5 | I42: 6 | J42: 7 | K42: 8 | L42: 9 | M42: 10 | N42: 11 | O42: 12 | P42: 13 | Q42: 14 | R42: 15 | S42: 16 | T42: 17 | U42: 18 | V42: 19 | W42: 20 | X42: 21 | Y42: 22 | Z42: 23 | AA42: 24 | AB42: 25 | AC42: 26 | AD42: 27 | AE42: 28 | AF42: 29 | AG42: 30 | AH42: 31 | AI42: 0 | AJ42: 0 | AK42: 0
A43: C2 | B43: 0 | C43: 51.851002 | D43: 306.08778 | E43: 89.593904 | F43: 430.80043 | G43: 173.07534 | H43: 36.46027 | I43: 28.571858 | J43: 118.7783 | K43: 52.61925 | L43: 339.42386 | M43: 106.90674 | N43: 448.25916 | O43: 162.42308 | P43: 45.028747 | Q43: 28.931966 | R43: 121.20085 | S43: 54.531889 | T43: 314.03184 | U43: 104.1767 | V43: 375.04583 | W43: 145.66362 | X43: 71.790178 | Y43: 32.795614 | Z43: 139.76897 | AA43: 57.236292 | AB43: 345.85736 | AC43: 103.78818 | AD43: 359.2045 | AE43: 220.83198 | AF43: 56.056449 | AG43: 8.4606457 | AH43: 128.18631 | AI43: 0 | AJ43: 0 | AK43: 1
A44: C3 | B44: 1 | C44: 1.0245254 | D44: 12.536708 | E44: 4.3301592 | F44: 19.704673 | G44: 79.44766 | H44: 0.51950732 | I44: 0.30657333 | J44: 5.1051911 | K44: 1.1325078 | L44: 11.2827 | M44: 5.7594264 | N44: 21.547138 | O44: 13.210476 | P44: 0.53377012 | Q44: 3.5060327 | R44: 4.4103609 | S44: 1.1887964 | T44: 10.473143 | U44: 4.3367428 | V44: 12.356597 | W44: 9.4964063 | X44: 0.93969452 | Y44: 6.0869213 | Z44: 4.5203226 | AA44: 1.2536237 | AB44: 11.167966 | AC44: 6.3988379 | AD44: 13.337994 | AE44: 294.20365 | AF44: 126.3414 | AG44: 3.4640644 | AH44: 5.7959954 | AI44: 0 | AJ44: 0 | AK44: 0
A45: C4 | B45: 2 | C45: 2.9674291 | D45: 64.411952 | E45: 6.6933575 | F45: 71.815228 | G45: 3.0295685e+16 | H45: 2.5401355 | I45: 1.9767586 | J45: 28.625336 | K45: 2.9674291 | L45: 71.252656 | M45: 11.321145 | N45: 72.293706 | O45: 26.215598 | P45: 2.4276943 | Q45: 3.0717112 | R45: 26.851699 | S45: 2.8260535 | T45: 72.486257 | U45: 9.8540689 | V45: 68.585113 | W45: 34.40891 | X45: 5.87431 | Y45: 5.0465956 | Z45: 27.463615 | AA45: 2.882681 | AB45: 63.248811 | AC45: 11.352681 | AD45: 61.683709 | AE45: 5.9594769 | AF45: 8.345479 | AG45: 0.27090021 | AH45: 28.118465 | AI45: 0 | AJ45: 0 | AK45: 0
A46: C5 | B46: 3 | C46: 32.557525 | D46: 45.645451 | E46: 15.857177 | F46: 78.612383 | G46: 91.775669 | H46: 30.48216 | I46: 8.2832552 | J46: 30.543309 | K46: 32.557525 | L46: 61.225513 | M46: 22.924158 | N46: 74.190908 | O46: 84.76475 | P46: 45.547215 | Q46: 9.3034753 | R46: 40.071096 | S46: 32.29427 | T46: 92.688141 | U46: 24.2584 | V46: 75.873249 | W46: 79.120523 | X46: 107.21904 | Y46: 10.104398 | Z46: 45.031661 | AA46: 33.019854 | AB46: 101.32806 | AC46: 26.550682 | AD46: 79.952324 | AE46: 13.596781 | AF46: 17.231423 | AG46: 6.7955251 | AH46: 46.979981 | AI46: 0 | AJ46: 0 | AK46: 0
A47: C6 | B47: 4 | C47: 23.14007 | D47: 194.32531 | E47: 21.70031 | F47: 139.26189 | G47: 62.51591 | H47: 26.890952 | I47: 8.6102106 | J47: 42.871796 | K47: 23.14007 | L47: 197.27114 | M47: 28.019765 | N47: 138.90734 | O47: 53.495304 | P47: 27.340645 | Q47: 8.1020645 | R47: 47.049476 | S47: 20.492505 | T47: 192.58693 | U47: 26.31837 | V47: 120.70306 | W47: 54.577684 | X47: 46.464739 | Y47: 9.0733122 | Z47: 54.166967 | AA47: 20.932371 | AB47: 204.44508 | AC47: 28.645778 | AD47: 130.98973 | AE47: 149.59756 | AF47: 47.918156 | AG47: 5.0579609 | AH47: 47.557284 | AI47: 0 | AJ47: 0 | AK47: 0
A48: C7 | B48: 5 | C48: 7.6531817 | D48: 44.685241 | E48: 21.716857 | F48: 69.126713 | G48: 48.467624 | H48: 6.0836636 | I48: 3.4093735 | J48: 51.186527 | K48: 7.2395022 | L48: 52.717053 | M48: 23.857215 | N48: 70.752955 | O48: 47.013043 | P48: 6.6608425 | Q48: 4.0174559 | R48: 41.119545 | S48: 7.6270758 | T48: 52.628489 | U48: 22.805876 | V48: 68.782125 | W48: 48.372106 | X48: 9.0726114 | Y48: 4.26203 | Z48: 45.761884 | AA48: 11.279482 | AB48: 50.57773 | AC48: 21.174483 | AD48: 68.353586 | AE48: 24.874047 | AF48: 3.410935 | AG48: 2.66306 | AH48: 48.861726 | AI48: 0 | AJ48: 0 | AK48: 0
A49: C8 | B49: 6 | C49: 16.256712 | D49: 82.448464 | E49: 80.369672 | F49: 289.38459 | G49: 104.89638 | H49: 20.030444 | I49: 22.089062 | J49: 177.10848 | K49: 16.14636 | L49: 101.41025 | M49: 83.685322 | N49: 275.29694 | O49: 97.233932 | P49: 13.078079 | Q49: 17.44849 | R49: 158.80912 | S49: 14.410575 | T49: 94.071046 | U49: 80.377255 | V49: 260.78527 | W49: 96.762069 | X49: 30.076272 | Y49: 14.862758 | Z49: 157.74329 | AA49: 19.478879 | AB49: 119.35403 | AC49: 76.447259 | AD49: 257.38784 | AE49: 154.6351 | AF49: 46.235791 | AG49: 0.54389883 | AH49: 128.45737 | AI49: 0 | AJ49: 0 | AK49: 1
A50: C9 | B50: 7 | C50: 26.384739 | D50: 274.51616 | E50: 88.613177 | F50: 458.13041 | G50: 218.6769 | H50: 32.701488 | I50: 23.485592 | J50: 139.59746 | K50: 26.310179 | L50: 316.43375 | M50: 111.76221 | N50: 460.86241 | O50: 195.03612 | P50: 30.930942 | Q50: 28.052597 | R50: 135.21647 | S50: 27.098534 | T50: 343.86567 | U50: 95.614035 | V50: 400.57301 | W50: 191.42119 | X50: 48.501216 | Y50: 30.432184 | Z50: 164.94175 | AA50: 32.907851 | AB50: 366.7076 | AC50: 99.26999 | AD50: 396.29277 | AE50: 272.49096 | AF50: 80.143506 | AG50: 6.3547983 | AH50: 138.70026 | AI50: 0 | AJ50: 0 | AK50: 1
A51: C10 | B51: 8 | C51: 5.0016793 | D51: 33.562384 | E51: 9.1131879 | F51: 64.78954 | G51: 37.952279 | H51: 18.249632 | I51: 6.1203972 | J51: 22.902023 | K51: 4.0057297 | L51: 37.10455 | M51: 9.4789146 | N51: 67.09809 | O51: 41.764545 | P51: 20.616917 | Q51: 6.0071993 | R51: 22.867267 | S51: 4.0210437 | T51: 42.83345 | U51: 11.954894 | V51: 64.437567 | W51: 40.675166 | X51: 23.985953 | Y51: 5.1385089 | Z51: 32.922111 | AA51: 5.2196843 | AB51: 52.21458 | AC51: 11.975029 | AD51: 63.100005 | AE51: 26.071256 | AF51: 13.061447 | AG51: 2.8261448 | AH51: 27.938995 | AI51: 0 | AJ51: 0 | AK51: 0
A52: C11 | B52: 9 | C52: 19.35283 | D52: 79.543681 | E52: 11.986869 | F52: 116.65401 | G52: 47.910905 | H52: 11.634562 | I52: 2.1198787 | J52: 62.800113 | K52: 18.634271 | L52: 89.552853 | M52: 14.967876 | N52: 110.13588 | O52: 47.188444 | P52: 8.5056431 | Q52: 7.0595948 | R52: 60.882753 | S52: 24.698954 | T52: 93.105677 | U52: 11.116214 | V52: 112.07819 | W52: 48.858889 | X52: 20.081062 | Y52: 0.1152675 | Z52: 58.807656 | AA52: 26.04855 | AB52: 94.552517 | AC52: 11.474711 | AD52: 112.24021 | AE52: 63.461971 | AF52: 11.813007 | AG52: 6.7770598 | AH52: 54.122061 | AI52: 0 | AJ52: 0 | AK52: 0
A53: C12 | B53: 10 | C53: 97.208034 | D53: 415.05036 | E53: 158.68255 | F53: 893.64199 | G53: 312.66391 | H53: 141.92388 | I53: 56.268777 | J53: 286.11451 | K53: 97.359695 | L53: 495.20198 | M53: 221.00748 | N53: 963.50621 | O53: 302.39481 | P53: 127.12392 | Q53: 65.191713 | R53: 300.37955 | S53: 94.023992 | T53: 503.03116 | U53: 184.65862 | V53: 903.07447 | W53: 288.31794 | X53: 162.07635 | Y53: 70.288364 | Z53: 409.38129 | AA53: 100.13821 | AB53: 554.05043 | AC53: 200.36898 | AD53: 911.21474 | AE53: 161.93735 | AF53: 141.90001 | AG53: 13.890108 | AH53: 340.13205 | AI53: 0 | AJ53: 0 | AK53: 1
A54: C13 | B54: 11 | C54: 3.60319 | D54: 139.01368 | E54: 15.314446 | F54: 139.97881 | G54: 67.637136 | H54: 5.9701525 | I54: 10.170596 | J54: 48.438257 | K54: 3.1541312 | L54: 152.6186 | M54: 15.749921 | N54: 152.0314 | O54: 70.760463 | P54: 4.5033589 | Q54: 7.7237069 | R54: 46.323378 | S54: 2.8014781 | T54: 146.97235 | U54: 15.938063 | V54: 112.94178 | W54: 62.343771 | X54: 6.4592683 | Y54: 11.861781 | Z54: 56.798393 | AA54: 2.8213828 | AB54: 145.7829 | AC54: 18.384834 | AD54: 127.35484 | AE54: 36.698388 | AF54: 22.054597 | AG54: 0.87903742 | AH54: 48.963905 | AI54: 0 | AJ54: 0 | AK54: 0
... A319: C215 | B319: 220 | C319: 28.920885 | D319: 254.23359 | E319: 159.5635 | F319: 321.45353 | G319: 106.67224 | H319: 27.925506 | I319: 16.103851 | J319: 241.0823 | K319: 28.920885 | L319: 292.3479 | M319: 144.60442 | N319: 368.69581 | O319: 100.61219 | P319: 16.955442 | Q319: 17.101123 | R319: 251.79344 | S319: 26.926341 | T319: 276.24558 | U319: 133.63443 | V319: 320.12274 | W319: 82.071297 | X319: 17.027447 | Y319: 26.00282 | Z319: 333.86548 | AA319: 26.926341 | AB319: 306.53022 | AC319: 142.68455 | AD319: 337.07636 | AE319: 34.904516 | AF319: 101.72207 | AG319: 0 | AH319: 277.02099 | AI319: 0 | AJ319: 0 | AK319: 1
B323: {=TRANSPOSE(A300:AK319)} -> C2 | C323: C8 | D323: C9 | E323: C12 | F323: C16 | G323: C22 | H323: C25 | I323: C27 | J323: C34 | K323: C37 | L323: C42 | M323: C74 | N323: C76 | O323: C77 | P323: C78 | Q323: C97 | R323: C98 | S323: C99 | T323: C114 | U323: C215
A324: document | B324: 0 | C324: 6 | D324: 7 | E324: 10 | F324: 14 | G324: 20 | H324: 23 | I324: 25 | J324: 32 | K324: 35 | L324: 40 | M324: 72 | N324: 74 | O324: 75 | P324: 76 | Q324: 95 | R324: 96 | S324: 97 | T324: 112 | U324: 220
A325: 0 | B325: 51.851002 | C325: 16.256712 | D325: 26.384739 | E325: 97.208034 | F325: 375.03324 | G325: 28.261021 | H325: 23.329239 | I325: 30.386693 | J325: 75.952829 | K325: 22.886214 | L325: 28.733223 | M325: 17.242799 | N325: 42.757097 | O325: 12.80601 | P325: 15.318453 | Q325: 7.4221752 | R325: 14.408651 | S325: 60.968428 | T325: 6.0823417 | U325: 28.920885
A326: 1 | B326: 306.08778 | C326: 82.448464 | D326: 274.51616 | E326: 415.05036 | F326: 1255.2543 | G326: 166.87932 | H326: 257.69948 | I326: 433.84638 | J326: 246.61223 | K326: 306.86222 | L326: 239.22045 | M326: 132.38438 | N326: 171.19988 | O326: 169.65558 | P326: 233.98395 | Q326: 18.442321 | R326: 122.63486 | S326: 203.92765 | T326: 331.30013 | U326: 254.23359
A327: 2 | B327: 89.593904 | C327: 80.369672 | D327: 88.613177 | E327: 158.68255 | F327: 376.95829 | G327: 28.346466 | H327: 106.97509 | I327: 65.232164 | J327: 81.955509 | K327: 155.31725 | L327: 56.668944 | M327: 19.647866 | N327: 45.323145 | O327: 32.056812 | P327: 49.996293 | Q327: 65.084435 | R327: 42.538984 | S327: 81.452215 | T327: 65.454006 | U327: 159.5635
A328: 3 | B328: 430.80043 | C328: 289.38459 | D328: 458.13041 | E328: 893.64199 | F328: 1775.6668 | G328: 185.60125 | H328: 300.2922 | I328: 327.92901 | J328: 447.34327 | K328: 373.00803 | L328: 263.04018 | M328: 91.354876 | N328: 216.61521 | O328: 248.512 | P328: 228.44635 | Q328: 304.19681 | R328: 151.64575 | S328: 285.88389 | T328: 158.61524 | U328: 321.45353
A329: 4 | B329: 173.07534 | C329: 104.89638 | D329: 218.6769 | E329: 312.66391 | F329: 1516.8056 | G329: 145.67565 | H329: 346.13357 | I329: 572.00817 | J329: 467.65299 | K329: 230.21074 | L329: 193.62484 | M329: 172.24455 | N329: 86.66805 | O329: 88.673098 | P329: 111.47116 | Q329: 164.15151 | R329: 158.4752 | S329: 228.24771 | T329: 107.82253 | U329: 106.67224
A330: 5 | B330: 36.46027 | C330: 20.030444 | D330: 32.701488 | E330: 141.92388 | F330: 573.86784 | G330: 20.934039 | H330: 98.002564 | I330: 226.7084 | J330: 202.14597 | K330: 71.353702 | L330: 45.739766 | M330: 32.321705 | N330: 114.97004 | O330: 56.683411 | P330: 38.282646 | Q330: 17.092669 | R330: 33.704955 | S330: 45.806265 | T330: 35.221286 | U330: 27.925506
A331: 6 | B331: 28.571858 | C331: 22.089062 | D331: 23.485592 | E331: 56.268777 | F331: 119.11851 | G331: 12.384452 | H331: 31.949681 | I331: 38.21749 | J331: 27.127527 | K331: 18.905042 | L331: 23.39172 | M331: 13.556458 | N331: 24.663616 | O331: 35.28264 | P331: 26.451461 | Q331: 10.103217 | R331: 37.636165 | S331: 22.717879 | T331: 8.103497 | U331: 16.103851
A332: 7 | B332: 118.7783 | C332: 177.10848 | D332: 139.59746 | E332: 286.11451 | F332: 839.18785 | G332: 113.52442 | H332: 219.06099 | I332: 173.52138 | J332: 169.89498 | K332: 118.68617 | L332: 148.5273 | M332: 130.85265 | N332: 105.54203 | O332: 72.910057 | P332: 140.56796 | Q332: 145.04998 | R332: 134.33116 | S332: 166.72636 | T332: 134.3404 | U332: 241.0823
A333: 8 | B333: 52.61925 | C333: 16.14636 | D333: 26.310179 | E333: 97.359695 | F333: 374.02271 | G333: 28.261021 | H333: 23.150731 | I333: 31.520711 | J333: 76.949132 | K333: 22.886214 | L333: 28.733223 | M333: 17.84907 | N333: 42.757097 | O333: 12.776513 | P333: 14.484706 | Q333: 7.4221752 | R333: 14.408651 | S333: 60.968428 | T333: 6.0823417 | U333: 28.920885
A334: 9 | B334: 339.42386 | C334: 101.41025 | D334: 316.43375 | E334: 495.20198 | F334: 1674.6148 | G334: 213.87614 | H334: 307.16552 | I334: 511.6289 | J334: 275.18271 | K334: 349.53829 | L334: 261.71155 | M334: 178.35642 | N334: 178.5729 | O334: 177.08365 | P334: 247.19361 | Q334: 21.664617 | R334: 189.24456 | S334: 245.05426 | T334: 372.69848 | U334: 292.3479
A335: 10 | B335: 106.90674 | C335: 83.685322 | D335: 111.76221 | E335: 221.00748 | F335: 465.86955 | G335: 36.764353 | H335: 133.04162 | I335: 134.2232 | J335: 158.85828 | K335: 182.29964 | L335: 75.807438 | M335: 26.332204 | N335: 65.087997 | O335: 46.068764 | P335: 52.751456 | Q335: 65.674718 | R335: 59.662397 | S335: 101.12361 | T335: 50.413623 | U335: 144.60442
A336: 11 | B336: 448.25916 | C336: 275.29694 | D336: 460.86241 | E336: 963.50621 | F336: 2032.6497 | G336: 196.39489 | H336: 322.38297 | I336: 324.39487 | J336: 502.48913 | K336: 402.03651 | L336: 285.22191 | M336: 92.859457 | N336: 226.24213 | O336: 255.22542 | P336: 237.57537 | Q336: 355.14789 | R336: 169.0051 | S336: 326.99985 | T336: 165.32031 | U336: 368.69581
... A356: 31 | B356: 128.18631 | C356: 128.45737 | D356: 138.70026 | E356: 340.13205 | F356: 1097.0339 | G356: 121.704 | H356: 216.18937 | I356: 205.89404 | J356: 235.64082 | K356: 134.72522 | L356: 111.0738 | M356: 201.34743 | N356: 109.06934 | O356: 69.879234 | P356: 144.01362 | Q356: 22.852795 | R356: 117.62825 | S356: 159.17837 | T356: 108.8612 | U356: 277.02099
B357: 0 | C357: 0 | D357: 0 | E357: 0 | F357: 0 | G357: 0 | H357: 0 | I357: 0 | J357: 0 | K357: 0 | L357: 0 | M357: 0 | N357: 0 | O357: 0 | P357: 0 | Q357: 0 | R357: 0 | S357: 0 | T357: 0 | U357: 0
B358: 0 | C358: 0 | D358: 0 | E358: 0 | F358: 0 | G358: 0 | H358: 0 | I358: 0 | J358: 0 | K358: 0 | L358: 0 | M358: 0 | N358: 0 | O358: 0 | P358: 0 | Q358: 0 | R358: 0 | S358: 0 | T358: 0 | U358: 0
B359: 1 | C359: 1 | D359: 1 | E359: 1 | F359: 1 | G359: 1 | H359: 1 | I359: 1 | J359: 1 | K359: 1 | L359: 1 | M359: 1 | N359: 1 | O359: 1 | P359: 1 | Q359: 1 | R359: 1 | S359: 1 | T359: 1 | U359: 1
